Workbook

Sheet Новости
A1: Единый реестр новостей муниципалитетов Республики Коми
A2: Одна публикация = одна строка. Основной муниципалитет обязателен; дополнительные перечисляйте через ;. Региональную новость вносить только при явной связи с муниципалитетом. Рабочий период — последние 30 дней; старые строки не удалять.
A3: Обязательное
A5: Сборщик | B5: Дата сбора | C5: Основной муниципалитет | D5: Дополнительные муниципалитеты | E5: Дата публикации | F5: Дата события | G5: Источник | H5: Прямая ссылка | I5: Дополнительные ссылки | J5: Заголовок | K5: Категория | L5: Стадия события | M5: Краткое фактическое резюме | N5: Ключевые цифры и факты | O5: Упомянутые лица | P5: Организации | Q5: ИНН из источника | R5: Объект/населённый пункт | S5: Возможный дубль | T5: Комментарий | U5: Автопроверка
A6: Python parser | B6: 2026-09-23 | C6: Республика Коми | E6: 2026-09-09 | G6: Государственный Совет Республики Коми | H6: https://www.gsrk.ru/presscenter/news/85584/ | J6: Александр Макаренко обсудил с Мариной Ким вопросы защиты пенсионных прав северян | K6: Власть и кадровые решения | L6: Встреча | M6: Александр Макаренко провел рабочую встречу с Мариной Ким для обсуждения вопросов защиты пенсионных прав северян и законодательных инициатив Республики Коми. | O6: Александр Макаренко, Марина Ким | P6: Государственный Совет Республики Коми, Комитет Государственной Думы по информационной политике, информационным технологиям и связи | R6: Сыктывкар | U6: =IF(COUNTA(A6:T6)=0,"",IF(OR(A6="",B6="",C6="",E6="",G6="",H6="",J6="",K6="",L6="",M6=""),"Ошибка: заполните обязательные поля",IF(AND(LEFT(H6,7)<>"http://",LEFT(H6,8)<>"https://"),"Ошибка: некорректная ссылка",IF(COUNTIF($H$6:$H$1005,H6)>1,"Ошибка: дубликат URL",IF(E6>TODAY(),"Ошибка: дата публикации в будущем",IF(S6="Да","Ошибка: подтверждённый дубль",IF(S6="","Проверить: отметьте дубль",IF(S6="Нужно проверить","Проверить возможный дубль",IF(TODAY()-E6>30,"Проверить: старше 30 дней",IF(COUNTIFS(#REF!,G6,#REF!,"Готово")=0,"Проверить источник","Готово"))))))))))
A7: Python parser | B7: 2026-09-23 | C7: Республика Коми | E7: 2026-09-09 | G7: Государственный Совет Республики Коми | H7: https://www.gsrk.ru/presscenter/news/85578/ | J7: Государственный Совет Коми стал площадкой для федерального диалога бизнеса и власти | K7: Экономика, бизнес и занятость | L7: Решение принято | M7: В Сыктывкаре прошёл форум предпринимателей с участием главы Коми и президента РСПП, где обсуждались вопросы поддержки деловой активности в условиях Севера и Арктики. | N7: Выдано микрозаймов на 2 млрд рублей; поручительства фонда на 3,5 млрд привлекли 9 млрд кредитных средств. | O7: Ростислав Гольдштейн (Глава Республики Коми), Александр Шохин (президент РСПП) | P7: Государственный Совет Республики Коми, Российский союз промышленников и предпринимателей | R7: Сыктывкар | U7: =IF(COUNTA(A7:T7)=0,"",IF(OR(A7="",B7="",C7="",E7="",G7="",H7="",J7="",K7="",L7="",M7=""),"Ошибка: заполните обязательные поля",IF(AND(LEFT(H7,7)<>"http://",LEFT(H7,8)<>"https://"),"Ошибка: некорректная ссылка",IF(COUNTIF($H$6:$H$1005,H7)>1,"Ошибка: дубликат URL",IF(E7>TODAY(),"Ошибка: дата публикации в будущем",IF(S7="Да","Ошибка: подтверждённый дубль",IF(S7="","Проверить: отметьте дубль",IF(S7="Нужно проверить","Проверить возможный дубль",IF(TODAY()-E7>30,"Проверить: старше 30 дней",IF(COUNTIFS(#REF!,G7,#REF!,"Готово")=0,"Проверить источник","Готово"))))))))))
A8: Python parser | B8: 2026-09-23 | C8: Республика Коми | E8: 2026-09-07 | G8: Государственный Совет Республики Коми | H8: https://www.gsrk.ru/presscenter/news/85462/ | J8: Александр Макаренко: «Качественная спортивная инфраструктура в районах — это основа здоровья наших граждан» | K8: Строительство и инфраструктура | L8: Работы начаты | M8: Руководство Республики Коми провело инспекцию строительства и модернизации спортивных объектов в Усть-Вымском районе, включая завершение возведения модульного спортивного зала в селе Айкино и капитальный ремонт Центра спорта и туризма в городе Микунь. | N8: Модульный спортивный зал в селе Айкино готов на 94%, ремонт Центра спорта и туризма в городе Микунь выполнен на 50%; подрядчики ООО «Каркас» и ООО «Исток»; финансирование осуществляется через соглашение о социальном партнерстве с компанией «ЛУКОЙЛ». | O8: Ростислав Гольдштейн (Глава Республики Коми), Александр Макаренко (Председатель Государственного Совета Республики Коми) | P8: ООО «Каркас», ООО «Исток», Правительство Коми, компания «ЛУКОЙЛ» | R8: Усть-Вымский район, село Айкино, город Микунь | U8: =IF(COUNTA(A8:T8)=0,"",IF(OR(A8="",B8="",C8="",E8="",G8="",H8="",J8="",K8="",L8="",M8=""),"Ошибка: заполните обязательные поля",IF(AND(LEFT(H8,7)<>"http://",LEFT(H8,8)<>"https://"),"Ошибка: некорректная ссылка",IF(COUNTIF($H$6:$H$1005,H8)>1,"Ошибка: дубликат URL",IF(E8>TODAY(),"Ошибка: дата публикации в будущем",IF(S8="Да","Ошибка: подтверждённый дубль",IF(S8="","Проверить: отметьте дубль",IF(S8="Нужно проверить","Проверить возможный дубль",IF(TODAY()-E8>30,"Проверить: старше 30 дней",IF(COUNTIFS(#REF!,G8,#REF!,"Готово")=0,"Проверить источник","Готово"))))))))))
A9: Python parser | B9: 2026-09-23 | C9: Республика Коми | E9: 2026-09-07 | G9: Государственный Совет Республики Коми | H9: https://www.gsrk.ru/presscenter/news/85461/ | J9: В Ухте открыли современный "Газпром-парк" площадью 10 гектаров | K9: Строительство и инфраструктура | L9: Завершено / открыто | M9: В Ухте открылся новый общественный парк 'Газпром-парк' площадью 10 гектаров, созданный на средства ПАО 'Газпром', включающий дорожки для прогулок, спортивные и детские площадки. | N9: Площадь парка - 10 гектаров; длина дорожек - более 6 км; наличие спортивных площадок для волейбола, бадминтона, настольного тенниса, скейт-парка и детских игровых зон; возможность зимнего катания на лыжах и коньках. | O9: Ростислав Гольдштейн (Глава Республики Коми), Александр Макаренко (Председатель Государственного Совета Республики Коми), Станислав Кочев (вице-спикер, Герой России), Владимир Блохин (депутат регионального парламента) | P9: ПАО 'Газпром' | R9: Ухта | U9: =IF(COUNTA(A9:T9)=0,"",IF(OR(A9="",B9="",C9="",E9="",G9="",H9="",J9="",K9="",L9="",M9=""),"Ошибка: заполните обязательные поля",IF(AND(LEFT(H9,7)<>"http://",LEFT(H9,8)<>"https://"),"Ошибка: некорректная ссылка",IF(COUNTIF($H$6:$H$1005,H9)>1,"Ошибка: дубликат URL",IF(E9>TODAY(),"Ошибка: дата публикации в будущем",IF(S9="Да","Ошибка: подтверждённый дубль",IF(S9="","Проверить: отметьте дубль",IF(S9="Нужно проверить","Проверить возможный дубль",IF(TODAY()-E9>30,"Проверить: старше 30 дней",IF(COUNTIFS(#REF!,G9,#REF!,"Готово")=0,"Проверить источник","Готово"))))))))))
A10: Python parser | B10: 2026-09-23 | C10: Республика Коми | E10: 2026-09-10 | G10: БНК | H10: https://www.bnkomi.ru/data/news/203119/ | J10: Малотравматичная операция новорожденному в РДКБ Коми | K10: Здравоохранение | L10: Результат | M10: В Республике Коми успешно проведена сложная малотравматичная операция новорожденному с опухолью надпочечника. Благодаря современному оборудованию и высокой квалификации врачей, вмешательство прошло успешно и минимально травматично для маленького пациента. | N10: 3,5-4 см | O10: Руслан Ислентьев, главный детский хирург Минздрава Коми, заместитель главного врача по хирургии РДКБ | P10: Республиканская детская клиническая больница | Q10: - | R10: Республика Коми | U10: =IF(COUNTA(A10:T10)=0,"",IF(OR(A10="",B10="",C10="",E10="",G10="",H10="",J10="",K10="",L10="",M10=""),"Ошибка: заполните обязательные поля",IF(AND(LEFT(H10,7)<>"http://",LEFT(H10,8)<>"https://"),"Ошибка: некорректная ссылка",IF(COUNTIF($H$6:$H$1005,H10)>1,"Ошибка: дубликат URL",IF(E10>TODAY(),"Ошибка: дата публикации в будущем",IF(S10="Да","Ошибка: подтверждённый дубль",IF(S10="","Проверить: отметьте дубль",IF(S10="Нужно проверить","Проверить возможный дубль",IF(TODAY()-E10>30,"Проверить: старше 30 дней",IF(COUNTIFS(#REF!,G10,#REF!,"Готово")=0,"Проверить источник","Готово"))))))))))
A11: Python parser | B11: 2026-09-23 | C11: Республика Коми | E11: 2026-09-10 | G11: БНК | H11: https://www.bnkomi.ru/data/news/203120/ | J11: Шохин обсудил поддержку инвестиций в Коми | K11: Экономика, бизнес и занятость | L11: Анонс | M11: Президент Российского союза промышленников и предпринимателей Александр Шохин посетил Республику Коми, где провел переговоры о поддержке инвестиционных проектов и мерах по стимулированию промышленного сектора в проекте бюджета на ближайшие годы. | N11: - | O11: Александр Шохин, президент Российского союза промышленников и предпринимателей; Ростислав Гольдштейн, глава Республики Коми | P11: Российский союз промышленников и предпринимателей, Коми союз промышленников и предпринимателей, ООО «Лузалес», ООО «Кофе плюс», Правительство Республики Коми, Минпромторг, Министерство экономического развития | Q11: - | R11: Сыктывкар, Республика Коми | U11: =IF(COUNTA(A11:T11)=0,"",IF(OR(A11="",B11="",C11="",E11="",G11="",H11="",J11="",K11="",L11="",M11=""),"Ошибка: заполните обязательные поля",IF(AND(LEFT(H11,7)<>"http://",LEFT(H11,8)<>"https://"),"Ошибка: некорректная ссылка",IF(COUNTIF($H$6:$H$1005,H11)>1,"Ошибка: дубликат URL",IF(E11>TODAY(),"Ошибка: дата публикации в будущем",IF(S11="Да","Ошибка: подтверждённый дубль",IF(S11="","Проверить: отметьте дубль",IF(S11="Нужно проверить","Проверить возможный дубль",IF(TODAY()-E11>30,"Проверить: старше 30 дней",IF(COUNTIFS(#REF!,G11,#REF!,"Готово")=0,"Проверить источник","Готово"))))))))))
A12: Python parser | B12: 2026-09-23 | C12: Республика Коми | E12: 2026-09-10 | G12: БНК | H12: https://www.bnkomi.ru/data/news/203121/ | J12: Поддержка семей в Республике Коми увеличивает рождаемость | K12: Социальная сфера | L12: Результат | M12: В рамках круглого стола обсуждалась эффективность мер поддержки семей с детьми в Республике Коми. Министр труда и соцзащиты Татьяна Майкова сообщила о положительной динамике рождаемости благодаря мерам государственной помощи, таких как семейный капитал и дополнительные выплаты. | N12: 37% (доля первенцев), 29% (прошлый показатель доли первенцев), 1,5 тыс. (прирост многодетных семей за 5 лет), 12 тыс. (число многодетных семей сейчас), 41 тыс. (дети в многодетных семьях) | O12: Татьяна Майкова (Министр труда и социальной защиты Республики Коми) | P12: - | Q12: - | R12: Сыктывкар | U12: =IF(COUNTA(A12:T12)=0,"",IF(OR(A12="",B12="",C12="",E12="",G12="",H12="",J12="",K12="",L12="",M12=""),"Ошибка: заполните обязательные поля",IF(AND(LEFT(H12,7)<>"http://",LEFT(H12,8)<>"https://"),"Ошибка: некорректная ссылка",IF(COUNTIF($H$6:$H$1005,H12)>1,"Ошибка: дубликат URL",IF(E12>TODAY(),"Ошибка: дата публикации в будущем",IF(S12="Да","Ошибка: подтверждённый дубль",IF(S12="","Проверить: отметьте дубль",IF(S12="Нужно проверить","Проверить возможный дубль",IF(TODAY()-E12>30,"Проверить: старше 30 дней",IF(COUNTIFS(#REF!,G12,#REF!,"Готово")=0,"Проверить источник","Готово"))))))))))
A13: Python parser | B13: 2026-09-23 | C13: Республика Коми | E13: 2026-09-10 | G13: БНК | H13: https://www.bnkomi.ru/data/news/196391/ | J13: Проект "Подарок новорожденному" в Республике Коми | K13: Социальная сфера | L13: В процессе | M13: Министерство труда и социальной защиты Республики Коми реализует проект "Подарок новорожденному", предоставляя наборы для младенцев. В комплект входит 19 предметов первой необходимости. На 2026 год выделен бюджет в размере 36,285 млн рублей. | N13: 5861 комплект в 2025 г., 812 комплектов за январь-февраль 2026 г., 36,285 млн руб. budget на 2026 г. | O13: - | P13: Министерство труда и социальной защиты Коми | Q13: - | R13: Республика Коми | U13: =IF(COUNTA(A13:T13)=0,"",IF(OR(A13="",B13="",C13="",E13="",G13="",H13="",J13="",K13="",L13="",M13=""),"Ошибка: заполните обязательные поля",IF(AND(LEFT(H13,7)<>"http://",LEFT(H13,8)<>"https://"),"Ошибка: некорректная ссылка",IF(COUNTIF($H$6:$H$1005,H13)>1,"Ошибка: дубликат URL",IF(E13>TODAY(),"Ошибка: дата публикации в будущем",IF(S13="Да","Ошибка: подтверждённый дубль",IF(S13="","Проверить: отметьте дубль",IF(S13="Нужно проверить","Проверить возможный дубль",IF(TODAY()-E13>30,"Проверить: старше 30 дней",IF(COUNTIFS(#REF!,G13,#REF!,"Готово")=0,"Проверить источник","Готово"))))))))))
A14: Python parser | B14: 2026-09-23 | C14: Республика Коми | E14: 2026-09-10 | G14: БНК | H14: https://www.bnkomi.ru/data/news/203127/ | J14: Перспективы нацгорного кластера в Коми обсудили с Александром Шохиным | K14: Экономика, бизнес и занятость | L14: Анонс | M14: Александр Шохин обсудил с руководством Коми инвестиционные проекты, включая создание национального горнопромышленного кластера на основе Пижемского месторождения титана и кварца. Проект реализуется компанией ГК «РУСТИТАН» при поддержке ведущих научных институтов России. | N14: - | O14: Александр Шохин, Ростислав Гольдштейн | P14: Российский союз промышленников и предпринимателей, ГК «РУСТИТАН», Институт металлургии и материаловедения им. А.А. Байкова Российской академии наук, Институт геологии рудных месторождений, петрографии, минералогии и геохимии Российской академии наук | Q14: - | R14: Республика Коми | U14: =IF(COUNTA(A14:T14)=0,"",IF(OR(A14="",B14="",C14="",E14="",G14="",H14="",J14="",K14="",L14="",M14=""),"Ошибка: заполните обязательные поля",IF(AND(LEFT(H14,7)<>"http://",LEFT(H14,8)<>"https://"),"Ошибка: некорректная ссылка",IF(COUNTIF($H$6:$H$1005,H14)>1,"Ошибка: дубликат URL",IF(E14>TODAY(),"Ошибка: дата публикации в будущем",IF(S14="Да","Ошибка: подтверждённый дубль",IF(S14="","Проверить: отметьте дубль",IF(S14="Нужно проверить","Проверить возможный дубль",IF(TODAY()-E14>30,"Проверить: старше 30 дней",IF(COUNTIFS(#REF!,G14,#REF!,"Готово")=0,"Проверить источник","Готово"))))))))))
A15: Python parser | B15: 2026-09-23 | C15: Республика Коми | E15: 2026-09-10 | G15: БНК | H15: https://www.bnkomi.ru/data/news/203128/ | J15: Развитие Северного морского пути обсудили в Сыктывкаре | K15: Экономика, бизнес и занятость | L15: Анонс | M15: Официальный представитель МИД России Мария Захарова обсудила перспективы развития Северного морского пути на выездном брифинге в Сыктывкаре. Она подчеркнула важность освоения Арктики и Северного морского пути для экономики и безопасности страны, отметив растущий интерес зарубежных партнеров к сотрудничеству в этой области. | N15: - | O15: Мария Захарова, Владимир Путин | P15: МИД России | Q15: - | R15: Республика Коми | U15: =IF(COUNTA(A15:T15)=0,"",IF(OR(A15="",B15="",C15="",E15="",G15="",H15="",J15="",K15="",L15="",M15=""),"Ошибка: заполните обязательные поля",IF(AND(LEFT(H15,7)<>"http://",LEFT(H15,8)<>"https://"),"Ошибка: некорректная ссылка",IF(COUNTIF($H$6:$H$1005,H15)>1,"Ошибка: дубликат URL",IF(E15>TODAY(),"Ошибка: дата публикации в будущем",IF(S15="Да","Ошибка: подтверждённый дубль",IF(S15="","Проверить: отметьте дубль",IF(S15="Нужно проверить","Проверить возможный дубль",IF(TODAY()-E15>30,"Проверить: старше 30 дней",IF(COUNTIFS(#REF!,G15,#REF!,"Готово")=0,"Проверить источник","Готово"))))))))))
A16: Python parser | B16: 2026-09-23 | C16: Республика Коми | E16: 2026-09-10 | G16: БНК | H16: https://www.bnkomi.ru/data/news/203129/ | J16: Ростислав Гольдштейн проведет прямую линию с жителями Коми | K16: Управление | L16: Анонс | M16: Сегодня в 18:00 Ростислав Гольдштейн ответит на вопросы жителей Республики Коми в прямом эфире. Колл-центр принимает вопросы по темам ЖКХ, благоустройства и дорог с использованием новой федеральной платформы обратной связи, что обеспечивает отслеживание всех обращений до их разрешения. | N16: - | O16: Ростислав Гольдштейн, Полина Разманова, Виталий Осипов | P16: Колл-центр, Министерство цифрового развития и связи Республики Коми, администрация главы и правительства Республики Коми | Q16: - | R16: Республика Коми | U16: =IF(COUNTA(A16:T16)=0,"",IF(OR(A16="",B16="",C16="",E16="",G16="",H16="",J16="",K16="",L16="",M16=""),"Ошибка: заполните обязательные поля",IF(AND(LEFT(H16,7)<>"http://",LEFT(H16,8)<>"https://"),"Ошибка: некорректная ссылка",IF(COUNTIF($H$6:$H$1005,H16)>1,"Ошибка: дубликат URL",IF(E16>TODAY(),"Ошибка: дата публикации в будущем",IF(S16="Да","Ошибка: подтверждённый дубль",IF(S16="","Проверить: отметьте дубль",IF(S16="Нужно проверить","Проверить возможный дубль",IF(TODAY()-E16>30,"Проверить: старше 30 дней",IF(COUNTIFS(#REF!,G16,#REF!,"Готово")=0,"Проверить источник","Готово"))))))))))
A17: Python parser | B17: 2026-09-23 | C17: Республика Коми | E17: 2026-09-10 | G17: БНК | H17: https://www.bnkomi.ru/data/news/203132/ | J17: Диалог Марии Захаровой о рисках конфликта в Арктике | K17: Власть и кадровые решения | L17: - | M17: Официальный представитель МИД России Мария Захарова заявила об усилении военной активности НАТО у северных границ страны и превращении Арктики в зону геополитической конфронтации. Она отметила, что Россия наблюдает за действиями альянса и готова принять необходимые меры для обеспечения своей безопасности, оставаясь при этом открытой для международного диалога. | N17: - | O17: Мария Захарова (официальный представитель МИД России) | P17: МИД России, НАТО, Минобороны России | Q17: - | R17: Арктика, Сыктывкар | U17: =IF(COUNTA(A17:T17)=0,"",IF(OR(A17="",B17="",C17="",E17="",G17="",H17="",J17="",K17="",L17="",M17=""),"Ошибка: заполните обязательные поля",IF(AND(LEFT(H17,7)<>"http://",LEFT(H17,8)<>"https://"),"Ошибка: некорректная ссылка",IF(COUNTIF($H$6:$H$1005,H17)>1,"Ошибка: дубликат URL",IF(E17>TODAY(),"Ошибка: дата публикации в будущем",IF(S17="Да","Ошибка: подтверждённый дубль",IF(S17="","Проверить: отметьте дубль",IF(S17="Нужно проверить","Проверить возможный дубль",IF(TODAY()-E17>30,"Проверить: старше 30 дней",IF(COUNTIFS(#REF!,G17,#REF!,"Готово")=0,"Проверить источник","Готово"))))))))))
A18: Python parser | B18: 2026-09-23 | C18: Воркута | E18: 2026-08-30 | G18: Воркута.Официально | H18: https://komiinform.ru/news/299815 | J18: Ростислав Гольдштейн поздравил шахтёров Воркуты с Днём шахтёра | K18: Власть и кадровые решения | L18: - | M18: Глава Республики Коми Ростислав Гольдштейн принял участие в праздновании Дня шахтёра в Воркуте, отметив вклад шахтеров в развитие региона и важность их работы для всей страны. Он также выразил благодарность жителям Воркуты за совместную работу по улучшению городской среды. | N18: - | O18: Ростислав Гольдштейн (Глава Республики Коми), Александр Макаренко (Председатель Государственного Совета Республики Коми) | P18: Государственный Совет Республики Коми | Q18: - | R18: Воркута | U18: =IF(COUNTA(A18:T18)=0,"",IF(OR(A18="",B18="",C18="",E18="",G18="",H18="",J18="",K18="",L18="",M18=""),"Ошибка: заполните обязательные поля",IF(AND(LEFT(H18,7)<>"http://",LEFT(H18,8)<>"https://"),"Ошибка: некорректная ссылка",IF(COUNTIF($H$6:$H$1005,H18)>1,"Ошибка: дубликат URL",IF(E18>TODAY(),"Ошибка: дата публикации в будущем",IF(S18="Да","Ошибка: подтверждённый дубль",IF(S18="","Проверить: отметьте дубль",IF(S18="Нужно проверить","Проверить возможный дубль",IF(TODAY()-E18>30,"Проверить: старше 30 дней",IF(COUNTIFS(#REF!,G18,#REF!,"Готово")=0,"Проверить источник","Готово"))))))))))
A19: Python parser | B19: 2026-09-23 | C19: Сыктывкар | E19: 2026-08-24 | G19: Максим Мартышин | H19: https://pos.gosuslugi.ru/lkp/direct-line/13583 | J19: Прямая линия с Главой Коми Гольдштейном | K19: Власть и кадровые решения | L19: В процессе | M19: Глава Республики Коми Ростислав Гольдштейн проводит прямую линию, принимает вопросы граждан от зарегистрированных пользователей ЕСИА. | N19: Дата начала: 24.08.2026 | O19: Гольдштейн Ростислав Эрнстович, Глава Республики Коми | P19: - | Q19: - | R19: Республика Коми | U19: =IF(COUNTA(A19:T19)=0,"",IF(OR(A19="",B19="",C19="",E19="",G19="",H19="",J19="",K19="",L19="",M19=""),"Ошибка: заполните обязательные поля",IF(AND(LEFT(H19,7)<>"http://",LEFT(H19,8)<>"https://"),"Ошибка: некорректная ссылка",IF(COUNTIF($H$6:$H$1005,H19)>1,"Ошибка: дубликат URL",IF(E19>TODAY(),"Ошибка: дата публикации в будущем",IF(S19="Да","Ошибка: подтверждённый дубль",IF(S19="","Проверить: отметьте дубль",IF(S19="Нужно проверить","Проверить возможный дубль",IF(TODAY()-E19>30,"Проверить: старше 30 дней",IF(COUNTIFS(#REF!,G19,#REF!,"Готово")=0,"Проверить источник","Готово"))))))))))
A20: Python parser | B20: 2026-09-23 | C20: Республика Коми | E20: 2026-09-10 | G20: Минобрнауки Коми | H20: http://fromkomi.ru/ | J20: Создание регионального бренда продуктов Коми | K20: Экономика, бизнес и занятость | L20: - | M20: В Республике Коми создается единый бренд для региональных продуктов питания, подчеркивающий их высокое качество, натуральность и местные традиции. | N20: - | O20: - | P20: - | Q20: - | R20: Республика Коми | U20: =IF(COUNTA(A20:T20)=0,"",IF(OR(A20="",B20="",C20="",E20="",G20="",H20="",J20="",K20="",L20="",M20=""),"Ошибка: заполните обязательные поля",IF(AND(LEFT(H20,7)<>"http://",LEFT(H20,8)<>"https://"),"Ошибка: некорректная ссылка",IF(COUNTIF($H$6:$H$1005,H20)>1,"Ошибка: дубликат URL",IF(E20>TODAY(),"Ошибка: дата публикации в будущем",IF(S20="Да","Ошибка: подтверждённый дубль",IF(S20="","Проверить: отметьте дубль",IF(S20="Нужно проверить","Проверить возможный дубль",IF(TODAY()-E20>30,"Проверить: старше 30 дней",IF(COUNTIFS(#REF!,G20,#REF!,"Готово")=0,"Проверить источник","Готово"))))))))))
A21: Python parser | B21: 2026-09-23 | C21: Республика Коми | E21: 2026-09-10 | G21: Минобрнауки Коми | H21: http://technogto.kruzhok.org/ | J21: Онлайн-марафон ТехноГТО 'Космическая квадрига' | K21: Образование | L21: Анонс | M21: В рамках проекта 'Таланты для космоса' пройдет онлайн-марафон ТехноГТО, где участники могут заработать дополнительные баллы к ЕГЭ и выиграть призы. Мероприятие рассчитано на школьников старших классов и студентов. | N21: 1 сентября 2026, 31 октября 2026, 10 дополнительных баллов | O21: - | P21: Проект 'Таланты для космоса' | Q21: - | R21: - | U21: =IF(COUNTA(A21:T21)=0,"",IF(OR(A21="",B21="",C21="",E21="",G21="",H21="",J21="",K21="",L21="",M21=""),"Ошибка: заполните обязательные поля",IF(AND(LEFT(H21,7)<>"http://",LEFT(H21,8)<>"https://"),"Ошибка: некорректная ссылка",IF(COUNTIF($H$6:$H$1005,H21)>1,"Ошибка: дубликат URL",IF(E21>TODAY(),"Ошибка: дата публикации в будущем",IF(S21="Да","Ошибка: подтверждённый дубль",IF(S21="","Проверить: отметьте дубль",IF(S21="Нужно проверить","Проверить возможный дубль",IF(TODAY()-E21>30,"Проверить: старше 30 дней",IF(COUNTIFS(#REF!,G21,#REF!,"Готово")=0,"Проверить источник","Готово"))))))))))
... A31: Python parser | B31: 2026-09-23 | C31: Республика Коми | E31: 2026-08-20 | G31: ГОЛОС РЕСПУБЛИКИ | H31: https://t.me/s/kompartya/14627 | J31: КПРФ в Республике Коми | K31: ВЫБОРЫ И ПАРТИИ | L31: - | M31: Новость касается деятельности Коммунистической партии Российской Федерации в Республике Коми. | N31: - | O31: - | P31: КПРФ | Q31: - | R31: Республика Коми | U31: =IF(COUNTA(A31:T31)=0,"",IF(OR(A31="",B31="",C31="",E31="",G31="",H31="",J31="",K31="",L31="",M31=""),"Ошибка: заполните обязательные поля",IF(AND(LEFT(H31,7)<>"http://",LEFT(H31,8)<>"https://"),"Ошибка: некорректная ссылка",IF(COUNTIF($H$6:$H$1005,H31)>1,"Ошибка: дубликат URL",IF(E31>TODAY(),"Ошибка: дата публикации в будущем",IF(S31="Да","Ошибка: подтверждённый дубль",IF(S31="","Проверить: отметьте дубль",IF(S31="Нужно проверить","Проверить возможный дубль",IF(TODAY()-E31>30,"Проверить: старше 30 дней",IF(COUNTIFS(#REF!,G31,#REF!,"Готово")=0,"Проверить источник","Готово"))))))))))
A32: Python parser | B32: 2026-09-23 | C32: Республика Коми | E32: 2026-09-03 | G32: Гольдштейн | Республика Коми | H32: https://t.me/s/goldshtein_komi | J32: Гольдштейн | Республика Коми | K32: Власть и кадровые решения | M32: Официальный Telegram-канал Главы Республики Коми Ростислава Гольдштейна. Актуальная информация о работе Правительства Республики Коми, решениях и событиях региона. Подписывайтесь, чтобы быть в курсе! Номер заявления для регистрации: 5955805962 | U32: =IF(COUNTA(A32:T32)=0,"",IF(OR(A32="",B32="",C32="",E32="",G32="",H32="",J32="",K32="",L32="",M32=""),"Ошибка: заполните обязательные поля",IF(AND(LEFT(H32,7)<>"http://",LEFT(H32,8)<>"https://"),"Ошибка: некорректная ссылка",IF(COUNTIF($H$6:$H$1005,H32)>1,"Ошибка: дубликат URL",IF(E32>TODAY(),"Ошибка: дата публикации в будущем",IF(S32="Да","Ошибка: подтверждённый дубль",IF(S32="","Проверить: отметьте дубль",IF(S32="Нужно проверить","Проверить возможный дубль",IF(TODAY()-E32>30,"Проверить: старше 30 дней",IF(COUNTIFS(#REF!,G32,#REF!,"Готово")=0,"Проверить источник","Готово"))))))))))
A33: Python parser | B33: 2026-09-23 | C33: Республика Коми | E33: 2026-09-08 | G33: Минэкономразвития и промышленности Республики Коми | H33: https://t.me/s/MinEcKomi | J33: Минэкономразвития и промышленности Республики Коми | K33: Экономика | M33: Офицальный канал Министерства экономического развития и промышленности Республики Коми Офицальный сайт: https://econom.rkomi.ru/ Вконтакте: https://vk.com/mineconomy11 | U33: =IF(COUNTA(A33:T33)=0,"",IF(OR(A33="",B33="",C33="",E33="",G33="",H33="",J33="",K33="",L33="",M33=""),"Ошибка: заполните обязательные поля",IF(AND(LEFT(H33,7)<>"http://",LEFT(H33,8)<>"https://"),"Ошибка: некорректная ссылка",IF(COUNTIF($H$6:$H$1005,H33)>1,"Ошибка: дубликат URL",IF(E33>TODAY(),"Ошибка: дата публикации в будущем",IF(S33="Да","Ошибка: подтверждённый дубль",IF(S33="","Проверить: отметьте дубль",IF(S33="Нужно проверить","Проверить возможный дубль",IF(TODAY()-E33>30,"Проверить: старше 30 дней",IF(COUNTIFS(#REF!,G33,#REF!,"Готово")=0,"Проверить источник","Готово"))))))))))
A34: Python parser | B34: 2026-09-23 | C34: Республика Коми | E34: 2026-09-04 | G34: Государственный Совет Республики Коми | H34: https://www.gsrk.ru/presscenter/news/85456/ | J34: Парламентские уроки в Коми посвятили теме единства и участию молодёжи в жизни республики | K34: Образование | L34: Решение принято | M34: Депутаты Государственного Совета Республики Коми провели парламентские уроки с молодежью, обсудив тему Года единства народов России и проект 'Команда Республики Коми', направленный на объединение активных граждан. | O34: Анастасия Михайлова (депутат, председатель Комитета по социальной политике), Ростислав Гольдштейн (Глава республики) | P34: Государственный Совет Республики Коми, Коми республиканский колледж культуры им. В.Т. Чисталева | R34: Республика Коми | U34: =IF(COUNTA(A34:T34)=0,"",IF(OR(A34="",B34="",C34="",E34="",G34="",H34="",J34="",K34="",L34="",M34=""),"Ошибка: заполните обязательные поля",IF(AND(LEFT(H34,7)<>"http://",LEFT(H34,8)<>"https://"),"Ошибка: некорректная ссылка",IF(COUNTIF($H$6:$H$1005,H34)>1,"Ошибка: дубликат URL",IF(E34>TODAY(),"Ошибка: дата публикации в будущем",IF(S34="Да","Ошибка: подтверждённый дубль",IF(S34="","Проверить: отметьте дубль",IF(S34="Нужно проверить","Проверить возможный дубль",IF(TODAY()-E34>30,"Проверить: старше 30 дней",IF(COUNTIFS(#REF!,G34,#REF!,"Готово")=0,"Проверить источник","Готово"))))))))))
A35: Python parser | B35: 2026-09-23 | C35: Республика Коми | E35: 2026-09-04 | G35: Государственный Совет Республики Коми | H35: https://www.gsrk.ru/presscenter/news/85430/ | J35: Александр Макаренко: Модернизация очистных сооружений в Микуни — результат совместной работы властей и контроля за запросами граждан | K35: Строительство и инфраструктура | L35: Завершено / открыто | M35: Завершилась модернизация очистных сооружений в городе Микунь, позволившая перейти на подземный водозабор, что улучшит качество питьевой воды. | O35: Александр Макаренко, Ростислав Гольдштейн | P35: Государственный Совет Республики Коми, Усть-Вымская тепловая компания | R35: Микунь | U35: =IF(COUNTA(A35:T35)=0,"",IF(OR(A35="",B35="",C35="",E35="",G35="",H35="",J35="",K35="",L35="",M35=""),"Ошибка: заполните обязательные поля",IF(AND(LEFT(H35,7)<>"http://",LEFT(H35,8)<>"https://"),"Ошибка: некорректная ссылка",IF(COUNTIF($H$6:$H$1005,H35)>1,"Ошибка: дубликат URL",IF(E35>TODAY(),"Ошибка: дата публикации в будущем",IF(S35="Да","Ошибка: подтверждённый дубль",IF(S35="","Проверить: отметьте дубль",IF(S35="Нужно проверить","Проверить возможный дубль",IF(TODAY()-E35>30,"Проверить: старше 30 дней",IF(COUNTIFS(#REF!,G35,#REF!,"Готово")=0,"Проверить источник","Готово"))))))))))
A36: Python parser | B36: 2026-09-23 | C36: Республика Коми | E36: 2026-09-03 | G36: Государственный Совет Республики Коми | H36: https://www.gsrk.ru/presscenter/news/85388/ | J36: I заседание III сессии Государственного Совета Республики Коми VIII созыва состоится 24 сентября 2026 года | K36: Власть и кадровые решения | L36: Анонс | M36: Председатель Государственного Совета Республики Коми А.П. Макаренко подписал распоряжение о проведении I заседания III сессии Государственного Совета Республики Коми VIII созыва 24 сентября 2026 года в городе Сыктывкаре с 10 часов в большом зале Государственного Совета Республики Коми по адресу: г. Сыктывкар ул. Коммунистическая, 8. | U36: =IF(COUNTA(A36:T36)=0,"",IF(OR(A36="",B36="",C36="",E36="",G36="",H36="",J36="",K36="",L36="",M36=""),"Ошибка: заполните обязательные поля",IF(AND(LEFT(H36,7)<>"http://",LEFT(H36,8)<>"https://"),"Ошибка: некорректная ссылка",IF(COUNTIF($H$6:$H$1005,H36)>1,"Ошибка: дубликат URL",IF(E36>TODAY(),"Ошибка: дата публикации в будущем",IF(S36="Да","Ошибка: подтверждённый дубль",IF(S36="","Проверить: отметьте дубль",IF(S36="Нужно проверить","Проверить возможный дубль",IF(TODAY()-E36>30,"Проверить: старше 30 дней",IF(COUNTIFS(#REF!,G36,#REF!,"Готово")=0,"Проверить источник","Готово"))))))))))
A37: Python parser | B37: 2026-09-23 | C37: Республика Коми | E37: 2026-09-09 | G37: Министерство закупок Республики Коми | H37: https://zakupki.rkomi.ru/presscenter/news/85600/ | J37: Суд: реестровая запись без сведений о баллах не подтверждает российское происхождение товара, если баллы установлены для вышестоящего кода ОКПД2 | K37: Закупки и контракты | M37: Суд рассмотрел дело о подтверждении российского происхождения спасательных гидрокостюмов при проведении электронного аукциона, указав, что реестровые записи без баллов не подтверждают происхождение товара. | N37: Начальная цена закупки около 1,5 млн рублей; ограничение по Постановлению № 1875; отсутствие реестровой записи у одного участника, некорректность информации у другого участника. | R37: Республика Коми | U37: =IF(COUNTA(A37:T37)=0,"",IF(OR(A37="",B37="",C37="",E37="",G37="",H37="",J37="",K37="",L37="",M37=""),"Ошибка: заполните обязательные поля",IF(AND(LEFT(H37,7)<>"http://",LEFT(H37,8)<>"https://"),"Ошибка: некорректная ссылка",IF(COUNTIF($H$6:$H$1005,H37)>1,"Ошибка: дубликат URL",IF(E37>TODAY(),"Ошибка: дата публикации в будущем",IF(S37="Да","Ошибка: подтверждённый дубль",IF(S37="","Проверить: отметьте дубль",IF(S37="Нужно проверить","Проверить возможный дубль",IF(TODAY()-E37>30,"Проверить: старше 30 дней",IF(COUNTIFS(#REF!,G37,#REF!,"Готово")=0,"Проверить источник","Готово"))))))))))
A38: Python parser | B38: 2026-09-23 | C38: Республика Коми | E38: 2026-09-07 | G38: Министерство закупок Республики Коми | H38: https://zakupki.rkomi.ru/presscenter/news/85470/ | J38: ЖКХ, дороги, здравоохранение: на Прямую линию с Главой Республики Коми Ростиславом Гольдштейном поступают вопросы жителей по самым актуальным темам. | K38: Обращения и проблемы жителей | L38: Анонс | M38: На сегодняшний день поступило порядка 1000 обращений. Большинство из них касается качества предоставления жилищно-коммунальных услуг, состояния дорог и доступности медицинской помощи. Напомним, 10 сентября Глава Республики Коми Ростислав Гольдштейн проведёт Прямую линию, совмещённую с пресс-конференцией. Задать свой вопрос руководителю региона можно: | U38: =IF(COUNTA(A38:T38)=0,"",IF(OR(A38="",B38="",C38="",E38="",G38="",H38="",J38="",K38="",L38="",M38=""),"Ошибка: заполните обязательные поля",IF(AND(LEFT(H38,7)<>"http://",LEFT(H38,8)<>"https://"),"Ошибка: некорректная ссылка",IF(COUNTIF($H$6:$H$1005,H38)>1,"Ошибка: дубликат URL",IF(E38>TODAY(),"Ошибка: дата публикации в будущем",IF(S38="Да","Ошибка: подтверждённый дубль",IF(S38="","Проверить: отметьте дубль",IF(S38="Нужно проверить","Проверить возможный дубль",IF(TODAY()-E38>30,"Проверить: старше 30 дней",IF(COUNTIFS(#REF!,G38,#REF!,"Готово")=0,"Проверить источник","Готово"))))))))))
A39: Python parser | B39: 2026-09-23 | C39: Республика Коми | E39: 2026-09-01 | G39: Министерство закупок Республики Коми | H39: https://zakupki.rkomi.ru/presscenter/news/85255/ | J39: Уважаемые заказчики Республики Коми! | K39: Закупки и контракты | M39: Министерство закупок Республики Коми обновило требования к представлению информации и документов, подтверждающих страну происхождения товаров для участия в закупках. | N39: Актуализированы формулировки требований; ссылка на официальный сайт министерства с примерами указаний; постановление Правительства РФ № 1875; Федеральный закон № 44-ФЗ. | P39: Министерство закупок Республики Коми | U39: =IF(COUNTA(A39:T39)=0,"",IF(OR(A39="",B39="",C39="",E39="",G39="",H39="",J39="",K39="",L39="",M39=""),"Ошибка: заполните обязательные поля",IF(AND(LEFT(H39,7)<>"http://",LEFT(H39,8)<>"https://"),"Ошибка: некорректная ссылка",IF(COUNTIF($H$6:$H$1005,H39)>1,"Ошибка: дубликат URL",IF(E39>TODAY(),"Ошибка: дата публикации в будущем",IF(S39="Да","Ошибка: подтверждённый дубль",IF(S39="","Проверить: отметьте дубль",IF(S39="Нужно проверить","Проверить возможный дубль",IF(TODAY()-E39>30,"Проверить: старше 30 дней",IF(COUNTIFS(#REF!,G39,#REF!,"Готово")=0,"Проверить источник","Готово"))))))))))
A40: Python parser | B40: 2026-09-23 | C40: Республика Коми | E40: 2026-09-02 | G40: Министерство здравоохранения Республики Коми | H40: https://minzdrav.rkomi.ru/presscenter/news/85290/ | J40: Будущее здравоохранения: министр поздравила студентов‑медиков Коми с началом учебного года | K40: Образование | L40: Анонс | M40: Министр здравоохранения Республики Коми Ирина Кондратьева поздравила студентов медицинских вузов и колледжей с началом учебного года и подчеркнула важность подготовки будущих специалистов для системы здравоохранения региона. | N40: В 2026 году систему здравоохранения республики пополнили 498 выпускников; 496 новых студентов начали обучение в медицинском колледже; в медицинский институт принято 116 человек на направления 'Лечебное дело' и 'Педиатрия'; в ординатуру зачислены 53 студента. | O40: Ирина Кондратьева - министр здравоохранения Республики Коми | P40: Сыктывкарский государственный университет, Сыктывкарский медицинский колледж, медицинский институт | R40: Республика Коми | U40: =IF(COUNTA(A40:T40)=0,"",IF(OR(A40="",B40="",C40="",E40="",G40="",H40="",J40="",K40="",L40="",M40=""),"Ошибка: заполните обязательные поля",IF(AND(LEFT(H40,7)<>"http://",LEFT(H40,8)<>"https://"),"Ошибка: некорректная ссылка",IF(COUNTIF($H$6:$H$1005,H40)>1,"Ошибка: дубликат URL",IF(E40>TODAY(),"Ошибка: дата публикации в будущем",IF(S40="Да","Ошибка: подтверждённый дубль",IF(S40="","Проверить: отметьте дубль",IF(S40="Нужно проверить","Проверить возможный дубль",IF(TODAY()-E40>30,"Проверить: старше 30 дней",IF(COUNTIFS(#REF!,G40,#REF!,"Готово")=0,"Проверить источник","Готово"))))))))))
A41: Python parser | B41: 2026-09-23 | C41: Республика Коми | E41: 2026-09-09 | G41: Министерство здравоохранения Республики Коми | H41: https://minzdrav.rkomi.ru/presscenter/news/85601/ | J41: 12 сентября — ваш шанс быстро и удобно проверить здоровье в Орбите! | K41: Здоровье | M41: 12 сентября в Орбите пройдет акция по проверке здоровья с различными медицинскими процедурами и тестами. | N41: Проведение акции с 10:00 до 15:00; виды медицинских процедур: измерение давления, проверка веса и роста, внутриглазного давления, уровня кислорода в крови, функции внешнего дыхания, экспресс-тесты на сахар и холестерин. | R41: Орбита | U41: =IF(COUNTA(A41:T41)=0,"",IF(OR(A41="",B41="",C41="",E41="",G41="",H41="",J41="",K41="",L41="",M41=""),"Ошибка: заполните обязательные поля",IF(AND(LEFT(H41,7)<>"http://",LEFT(H41,8)<>"https://"),"Ошибка: некорректная ссылка",IF(COUNTIF($H$6:$H$1005,H41)>1,"Ошибка: дубликат URL",IF(E41>TODAY(),"Ошибка: дата публикации в будущем",IF(S41="Да","Ошибка: подтверждённый дубль",IF(S41="","Проверить: отметьте дубль",IF(S41="Нужно проверить","Проверить возможный дубль",IF(TODAY()-E41>30,"Проверить: старше 30 дней",IF(COUNTIFS(#REF!,G41,#REF!,"Готово")=0,"Проверить источник","Готово"))))))))))
A42: Python parser | B42: 2026-09-23 | C42: Республика Коми | E42: 2026-09-04 | G42: Министерство здравоохранения Республики Коми | H42: https://minzdrav.rkomi.ru/presscenter/news/85458/ | J42: Электронное голосование | K42: Власть и кадровые решения | L42: Анонс | M42: На выборах в Коми применяют несколько форм голосования, среди которых есть дистанционное электронное голосование (ДЭГ) . До 14 сентября принимают заявления о включении в список избирателей для участия в ДЭГ и для голосования по месту нахождения. | U42: =IF(COUNTA(A42:T42)=0,"",IF(OR(A42="",B42="",C42="",E42="",G42="",H42="",J42="",K42="",L42="",M42=""),"Ошибка: заполните обязательные поля",IF(AND(LEFT(H42,7)<>"http://",LEFT(H42,8)<>"https://"),"Ошибка: некорректная ссылка",IF(COUNTIF($H$6:$H$1005,H42)>1,"Ошибка: дубликат URL",IF(E42>TODAY(),"Ошибка: дата публикации в будущем",IF(S42="Да","Ошибка: подтверждённый дубль",IF(S42="","Проверить: отметьте дубль",IF(S42="Нужно проверить","Проверить возможный дубль",IF(TODAY()-E42>30,"Проверить: старше 30 дней",IF(COUNTIFS(#REF!,G42,#REF!,"Готово")=0,"Проверить источник","Готово"))))))))))
A43: Python parser | B43: 2026-09-23 | C43: Республика Коми | E43: 2026-09-04 | G43: Министерство здравоохранения Республики Коми | H43: https://minzdrav.rkomi.ru/presscenter/news/85451/ | J43: 10 сентября Глава Республики Коми Ростислав Гольдштейн проведёт Прямую линию, совмещённую с пресс-конференцией | K43: Власть и кадровые решения | L43: Решение принято | M43: ЖКХ, дороги, здравоохранение: на Прямую линию с Главой Республики Коми Ростиславом Гольдштейном поступают вопросы жителей по самым актуальным темам. На сегодняшний день поступило порядка 1000 обращений. Большинство из них касается качества предоставления жилищно-коммунальных услуг, состояния дорог и доступности медицинской помощи. Напомним, 10 сентября Глава Республики Коми Ростислав Гольдштейн проведёт Прямую линию, совмещённую с пресс-конференцией. | U43: =IF(COUNTA(A43:T43)=0,"",IF(OR(A43="",B43="",C43="",E43="",G43="",H43="",J43="",K43="",L43="",M43=""),"Ошибка: заполните обязательные поля",IF(AND(LEFT(H43,7)<>"http://",LEFT(H43,8)<>"https://"),"Ошибка: некорректная ссылка",IF(COUNTIF($H$6:$H$1005,H43)>1,"Ошибка: дубликат URL",IF(E43>TODAY(),"Ошибка: дата публикации в будущем",IF(S43="Да","Ошибка: подтверждённый дубль",IF(S43="","Проверить: отметьте дубль",IF(S43="Нужно проверить","Проверить возможный дубль",IF(TODAY()-E43>30,"Проверить: старше 30 дней",IF(COUNTIFS(#REF!,G43,#REF!,"Готово")=0,"Проверить источник","Готово"))))))))))
A44: Python parser | B44: 2026-09-23 | C44: Республика Коми | E44: 2026-09-01 | G44: Министерство здравоохранения Республики Коми | H44: https://minzdrav.rkomi.ru/presscenter/news/84269/ | J44: Как подготовиться к рождению ребенка расскажет портал «Госуслуги» | K44: Социальная сфера | M44: На портале 'Госуслуги' размещена информация о подготовке к беременности и родам, включая необходимые документы и рекомендации. | N44: Жизненная ситуация 'Планирование и рождение ребенка' включает этапы планирования беременности, ведения беременности и рождения ребенка; требуется подготовка перед отправкой в роддом; после рождения ребенка можно оформить свидетельство о рождении онлайн; СНИЛС и полис ОМС новорожденному присваиваются автоматически. | R44: Республика Коми | U44: =IF(COUNTA(A44:T44)=0,"",IF(OR(A44="",B44="",C44="",E44="",G44="",H44="",J44="",K44="",L44="",M44=""),"Ошибка: заполните обязательные поля",IF(AND(LEFT(H44,7)<>"http://",LEFT(H44,8)<>"https://"),"Ошибка: некорректная ссылка",IF(COUNTIF($H$6:$H$1005,H44)>1,"Ошибка: дубликат URL",IF(E44>TODAY(),"Ошибка: дата публикации в будущем",IF(S44="Да","Ошибка: подтверждённый дубль",IF(S44="","Проверить: отметьте дубль",IF(S44="Нужно проверить","Проверить возможный дубль",IF(TODAY()-E44>30,"Проверить: старше 30 дней",IF(COUNTIFS(#REF!,G44,#REF!,"Готово")=0,"Проверить источник","Готово"))))))))))
A45: Python parser | B45: 2026-09-23 | C45: Республика Коми | E45: 2026-08-31 | G45: Министерство здравоохранения Республики Коми | H45: https://minzdrav.rkomi.ru/presscenter/news/84733/ | J45: «Прогулки меняют»: в Воркуте с паллиативными пациентами больницы гуляют добровольцы | K45: Социальная сфера | M45: Воркутинская больница скорой помощи запустила проект 'Прогулки доброты', при котором добровольцы гуляют с паллиативными пациентами на свежем воздухе, улучшая их настроение. | O45: Галина Курдюкова (главная медицинская сестра воркутинской больницы) | P45: Воркутинская больница скорой помощи | R45: Воркута | U45: =IF(COUNTA(A45:T45)=0,"",IF(OR(A45="",B45="",C45="",E45="",G45="",H45="",J45="",K45="",L45="",M45=""),"Ошибка: заполните обязательные поля",IF(AND(LEFT(H45,7)<>"http://",LEFT(H45,8)<>"https://"),"Ошибка: некорректная ссылка",IF(COUNTIF($H$6:$H$1005,H45)>1,"Ошибка: дубликат URL",IF(E45>TODAY(),"Ошибка: дата публикации в будущем",IF(S45="Да","Ошибка: подтверждённый дубль",IF(S45="","Проверить: отметьте дубль",IF(S45="Нужно проверить","Проверить возможный дубль",IF(TODAY()-E45>30,"Проверить: старше 30 дней",IF(COUNTIFS(#REF!,G45,#REF!,"Готово")=0,"Проверить источник","Готово"))))))))))
A46: Python parser | B46: 2026-09-23 | C46: Республика Коми | E46: 2026-08-28 | G46: Министерство здравоохранения Республики Коми | H46: https://minzdrav.rkomi.ru/presscenter/news/85179/ | J46: Заботьтесь о здоровье по субботам! | K46: Здравоохранение | L46: Решение принято | M46: С 29 августа в пгт Краснозатонский будет работать мобильный флюорограф для обследования легких жителей. | N46: Время работы: с 10:00 до 14:00; Место проведения: площадь им. Е.В. Чепыгина; Целевая аудитория: жители пгт Краснозатонский. | R46: пгт Краснозатонский | U46: =IF(COUNTA(A46:T46)=0,"",IF(OR(A46="",B46="",C46="",E46="",G46="",H46="",J46="",K46="",L46="",M46=""),"Ошибка: заполните обязательные поля",IF(AND(LEFT(H46,7)<>"http://",LEFT(H46,8)<>"https://"),"Ошибка: некорректная ссылка",IF(COUNTIF($H$6:$H$1005,H46)>1,"Ошибка: дубликат URL",IF(E46>TODAY(),"Ошибка: дата публикации в будущем",IF(S46="Да","Ошибка: подтверждённый дубль",IF(S46="","Проверить: отметьте дубль",IF(S46="Нужно проверить","Проверить возможный дубль",IF(TODAY()-E46>30,"Проверить: старше 30 дней",IF(COUNTIFS(#REF!,G46,#REF!,"Готово")=0,"Проверить источник","Готово"))))))))))
A47: Python parser | B47: 2026-09-23 | C47: Республика Коми | E47: 2026-09-07 | G47: Министерство имущественных и земельных отношений Республики Коми | H47: https://agui.rkomi.ru/presscenter/news/85467/ | J47: ЖКХ, дороги, здравоохранение: на Прямую линию с Главой Республики Коми Ростиславом Гольдштейном поступают вопросы жителей по самым актуальным темам | K47: Обращения и проблемы жителей | L47: Проблема / происшествие | M47: ЖКХ, дороги, здравоохранение: на Прямую линию с Главой Республики Коми Ростиславом Гольдштейном поступают вопросы жителей по самым актуальным темам | U47: =IF(COUNTA(A47:T47)=0,"",IF(OR(A47="",B47="",C47="",E47="",G47="",H47="",J47="",K47="",L47="",M47=""),"Ошибка: заполните обязательные поля",IF(AND(LEFT(H47,7)<>"http://",LEFT(H47,8)<>"https://"),"Ошибка: некорректная ссылка",IF(COUNTIF($H$6:$H$1005,H47)>1,"Ошибка: дубликат URL",IF(E47>TODAY(),"Ошибка: дата публикации в будущем",IF(S47="Да","Ошибка: подтверждённый дубль",IF(S47="","Проверить: отметьте дубль",IF(S47="Нужно проверить","Проверить возможный дубль",IF(TODAY()-E47>30,"Проверить: старше 30 дней",IF(COUNTIFS(#REF!,G47,#REF!,"Готово")=0,"Проверить источник","Готово"))))))))))
A48: Python parser | B48: 2026-09-23 | C48: Республика Коми | E48: 2026-09-03 | G48: Министерство имущественных и земельных отношений Республики Коми | H48: https://agui.rkomi.ru/presscenter/news/85407/ | J48: «Команда Республики Коми» взяла на контроль транспортную доступность в селе Озёл и пст Трехозерка | K48: Происшествия и безопасность | L48: Проблема / происшествие | M48: Министры и глава муниципалитета провели встречу с жителями села Озёл и посёлка Трехозерка для обсуждения транспортных и медицинских проблем, регистрации безработных, отсутствия сотовой связи и получения пенсионных выплат. | N48: Проведена встреча с жителями; обсуждались транспортные и медицинские проблемы, регистрация безработных, отсутствие сотовой связи, получение пенсионных выплат; министры и глава муниципалитета прошли по окрестностям села и осмотрели имущественные объекты. | O48: Людмила Забоева (Министр имущественных и земельных отношений РК), Ирина Кондратьева (Министр здравоохранения РК), Илья Семяшкин (Глава МР «Сыктывдинский»), Наталья Сурадейкина (глава поселения) | P48: Республика Коми, Министерство имущественных и земельных отношений РК, Министерство здравоохранения РК, МР «Сыктывдинский» | R48: село Озёл, посёлок Трехозерка | U48: =IF(COUNTA(A48:T48)=0,"",IF(OR(A48="",B48="",C48="",E48="",G48="",H48="",J48="",K48="",L48="",M48=""),"Ошибка: заполните обязательные поля",IF(AND(LEFT(H48,7)<>"http://",LEFT(H48,8)<>"https://"),"Ошибка: некорректная ссылка",IF(COUNTIF($H$6:$H$1005,H48)>1,"Ошибка: дубликат URL",IF(E48>TODAY(),"Ошибка: дата публикации в будущем",IF(S48="Да","Ошибка: подтверждённый дубль",IF(S48="","Проверить: отметьте дубль",IF(S48="Нужно проверить","Проверить возможный дубль",IF(TODAY()-E48>30,"Проверить: старше 30 дней",IF(COUNTIFS(#REF!,G48,#REF!,"Готово")=0,"Проверить источник","Готово"))))))))))
A49: Python parser | B49: 2026-09-23 | C49: Республика Коми | E49: 2026-09-02 | G49: Министерство имущественных и земельных отношений Республики Коми | H49: https://agui.rkomi.ru/presscenter/news/85286/ | J49: Республика Коми получила дивиденды от государственных компаний за 2025 год | K49: Муниципальные финансы | M49: В 2026 году в бюджет Республики Коми поступили дивиденды от 10 государственных компаний на сумму 553,01 млн рублей, впервые от акционерного общества «Коми дорожная компания». Средства направляются на социальные программы и стратегические проекты. | N49: Сумма поступивших дивидендов: 553,01 млн рублей; впервые дивиденды получены от АО «Коми дорожная компания»; средства будут направлены на социальные программы и развитие региона. | R49: Республика Коми | U49: =IF(COUNTA(A49:T49)=0,"",IF(OR(A49="",B49="",C49="",E49="",G49="",H49="",J49="",K49="",L49="",M49=""),"Ошибка: заполните обязательные поля",IF(AND(LEFT(H49,7)<>"http://",LEFT(H49,8)<>"https://"),"Ошибка: некорректная ссылка",IF(COUNTIF($H$6:$H$1005,H49)>1,"Ошибка: дубликат URL",IF(E49>TODAY(),"Ошибка: дата публикации в будущем",IF(S49="Да","Ошибка: подтверждённый дубль",IF(S49="","Проверить: отметьте дубль",IF(S49="Нужно проверить","Проверить возможный дубль",IF(TODAY()-E49>30,"Проверить: старше 30 дней",IF(COUNTIFS(#REF!,G49,#REF!,"Готово")=0,"Проверить источник","Готово"))))))))))
A50: Python parser | B50: 2026-09-23 | C50: Республика Коми | E50: 2026-09-02 | G50: Министерство имущественных и земельных отношений Республики Коми | H50: https://agui.rkomi.ru/presscenter/news/85285/ | J50: Как задать вопрос Главе Коми? Ростислав Гольдштейн проведет прямую линию 10 сентября. | K50: Другое | L50: Анонс | M50: Как задать вопрос Главе Коми? Ростислав Гольдштейн проведет прямую линию 10 сентября. | U50: =IF(COUNTA(A50:T50)=0,"",IF(OR(A50="",B50="",C50="",E50="",G50="",H50="",J50="",K50="",L50="",M50=""),"Ошибка: заполните обязательные поля",IF(AND(LEFT(H50,7)<>"http://",LEFT(H50,8)<>"https://"),"Ошибка: некорректная ссылка",IF(COUNTIF($H$6:$H$1005,H50)>1,"Ошибка: дубликат URL",IF(E50>TODAY(),"Ошибка: дата публикации в будущем",IF(S50="Да","Ошибка: подтверждённый дубль",IF(S50="","Проверить: отметьте дубль",IF(S50="Нужно проверить","Проверить возможный дубль",IF(TODAY()-E50>30,"Проверить: старше 30 дней",IF(COUNTIFS(#REF!,G50,#REF!,"Готово")=0,"Проверить источник","Готово"))))))))))
A51: Python parser | B51: 2026-09-23 | C51: Республика Коми | E51: 2026-09-01 | G51: Министерство имущественных и земельных отношений Республики Коми | H51: https://agui.rkomi.ru/presscenter/news/85269/ | J51: Торжественная линейка и поздравления: в Выльгорте начался новый учебный год | K51: Образование | L51: Решение принято | M51: В МБОУ «Выльгортская средняя общеобразовательная школа №2» имени В. П. Налимова состоялся торжественный старт нового учебного года после капитального ремонта школы. | N51: Капитальный ремонт школы завершён; мероприятие посетили первые и одиннадцатые классы; почетным гостем был Глава Республики Коми Ростислав Гольдштейн. | O51: Ростислав Гольдштейн (Глава Республики Коми) | P51: МБОУ «Выльгортская средняя общеобразовательная школа №2» имени В. П. Налимова | R51: село Выльгорт, Сыктывдинский район | U51: =IF(COUNTA(A51:T51)=0,"",IF(OR(A51="",B51="",C51="",E51="",G51="",H51="",J51="",K51="",L51="",M51=""),"Ошибка: заполните обязательные поля",IF(AND(LEFT(H51,7)<>"http://",LEFT(H51,8)<>"https://"),"Ошибка: некорректная ссылка",IF(COUNTIF($H$6:$H$1005,H51)>1,"Ошибка: дубликат URL",IF(E51>TODAY(),"Ошибка: дата публикации в будущем",IF(S51="Да","Ошибка: подтверждённый дубль",IF(S51="","Проверить: отметьте дубль",IF(S51="Нужно проверить","Проверить возможный дубль",IF(TODAY()-E51>30,"Проверить: старше 30 дней",IF(COUNTIFS(#REF!,G51,#REF!,"Готово")=0,"Проверить источник","Готово"))))))))))
A52: Python parser | B52: 2026-09-23 | C52: Республика Коми | E52: 2026-07-14 | G52: ГОЛОС РЕСПУБЛИКИ | H52: https://t.me/s/rkomivoice | J52: ГОЛОС РЕСПУБЛИКИ | K52: Власть и кадровые решения | M52: Олег Михайлов, депутат Государственной Думы от Республики Коми (фракция КПРФ) | U52: =IF(COUNTA(A52:T52)=0,"",IF(OR(A52="",B52="",C52="",E52="",G52="",H52="",J52="",K52="",L52="",M52=""),"Ошибка: заполните обязательные поля",IF(AND(LEFT(H52,7)<>"http://",LEFT(H52,8)<>"https://"),"Ошибка: некорректная ссылка",IF(COUNTIF($H$6:$H$1005,H52)>1,"Ошибка: дубликат URL",IF(E52>TODAY(),"Ошибка: дата публикации в будущем",IF(S52="Да","Ошибка: подтверждённый дубль",IF(S52="","Проверить: отметьте дубль",IF(S52="Нужно проверить","Проверить возможный дубль",IF(TODAY()-E52>30,"Проверить: старше 30 дней",IF(COUNTIFS(#REF!,G52,#REF!,"Готово")=0,"Проверить источник","Готово"))))))))))
A53: Python parser | B53: 2026-09-23 | C53: Республика Коми | E53: 2026-09-01 | G53: Министерство имущественных и земельных отношений Республики Коми | H53: https://agui.rkomi.ru/presscenter/news/85237/ | J53: На площадке «Команды Республики Коми» обсудили будущее Выльгорта: дороги, безопасность и коммуникации | K53: Происшествия и безопасность | L53: Проблема / происшествие | M53: На встрече в музее Сыктывдинского района представители власти обсудили проблемы села Выльгорт, такие как состояние дорог, безопасность и обеспечение коммуникациями. | O53: Людмила Забоева - министр имущественных и земельных отношений Республики Коми, Илья Семяшкин - глава Сыктывдинского района | P53: Штаб общественной поддержки «Команда Республики Коми», музей истории и культуры Сыктывдинского района имени Э.А. Налимовой | R53: Выльгорт | U53: =IF(COUNTA(A53:T53)=0,"",IF(OR(A53="",B53="",C53="",E53="",G53="",H53="",J53="",K53="",L53="",M53=""),"Ошибка: заполните обязательные поля",IF(AND(LEFT(H53,7)<>"http://",LEFT(H53,8)<>"https://"),"Ошибка: некорректная ссылка",IF(COUNTIF($H$6:$H$1005,H53)>1,"Ошибка: дубликат URL",IF(E53>TODAY(),"Ошибка: дата публикации в будущем",IF(S53="Да","Ошибка: подтверждённый дубль",IF(S53="","Проверить: отметьте дубль",IF(S53="Нужно проверить","Проверить возможный дубль",IF(TODAY()-E53>30,"Проверить: старше 30 дней",IF(COUNTIFS(#REF!,G53,#REF!,"Готово")=0,"Проверить источник","Готово"))))))))))
A54: Python parser | B54: 2026-09-23 | C54: Республика Коми | E54: 2026-08-28 | G54: Министерство имущественных и земельных отношений Республики Коми | H54: https://agui.rkomi.ru/presscenter/news/85159/ | J54: Доброе дело в Министерстве: сотрудники помогли бездомным животным | K54: Социальная сфера | M54: Сотрудники Министерства имущественных и земельных отношений Республики Коми и ГБУ РК собрали большое количество сухого и влажного корма для приютов 'Друг', 'Кошкин Дом' и 'Кошки за окошком'. | N54: Собрано значительное количество кормов; передано в три приюта. | R54: Республика Коми | U54: =IF(COUNTA(A54:T54)=0,"",IF(OR(A54="",B54="",C54="",E54="",G54="",H54="",J54="",K54="",L54="",M54=""),"Ошибка: заполните обязательные поля",IF(AND(LEFT(H54,7)<>"http://",LEFT(H54,8)<>"https://"),"Ошибка: некорректная ссылка",IF(COUNTIF($H$6:$H$1005,H54)>1,"Ошибка: дубликат URL",IF(E54>TODAY(),"Ошибка: дата публикации в будущем",IF(S54="Да","Ошибка: подтверждённый дубль",IF(S54="","Проверить: отметьте дубль",IF(S54="Нужно проверить","Проверить возможный дубль",IF(TODAY()-E54>30,"Проверить: старше 30 дней",IF(COUNTIFS(#REF!,G54,#REF!,"Готово")=0,"Проверить источник","Готово"))))))))))
A55: Python parser | B55: 2026-09-23 | C55: Республика Коми | E55: 2026-08-27 | G55: Министерство имущественных и земельных отношений Республики Коми | H55: https://agui.rkomi.ru/presscenter/news/85142/ | J55: Минимущества Республики Коми сообщает о продаже недвижимого имущества на аукционе в электронной форме | K55: Закупки и контракты | M55: Министерство имущественных отношений Республики Коми проводит аукцион в электронной форме по продаже нескольких зданий и земельных участков в различных населенных пунктах республики. | N55: Предлагается к продаже недвижимое имущество общей площадью более 6 тысяч квадратных метров, включая здания и участки в городах Сыктывкар и Воркута, а также сельских поселениях Выльгорт и Лэзым. | R55: Сыктывкар, Воркута, Сыктывдинский район, село Выльгорт, село Лэзым | U55: =IF(COUNTA(A55:T55)=0,"",IF(OR(A55="",B55="",C55="",E55="",G55="",H55="",J55="",K55="",L55="",M55=""),"Ошибка: заполните обязательные поля",IF(AND(LEFT(H55,7)<>"http://",LEFT(H55,8)<>"https://"),"Ошибка: некорректная ссылка",IF(COUNTIF($H$6:$H$1005,H55)>1,"Ошибка: дубликат URL",IF(E55>TODAY(),"Ошибка: дата публикации в будущем",IF(S55="Да","Ошибка: подтверждённый дубль",IF(S55="","Проверить: отметьте дубль",IF(S55="Нужно проверить","Проверить возможный дубль",IF(TODAY()-E55>30,"Проверить: старше 30 дней",IF(COUNTIFS(#REF!,G55,#REF!,"Готово")=0,"Проверить источник","Готово"))))))))))
A56: Python parser | B56: 2026-09-23 | C56: Республика Коми | E56: 2026-08-26 | G56: Министерство имущественных и земельных отношений Республики Коми | H56: https://agui.rkomi.ru/presscenter/news/85087/ | J56: Ростислав Гольдштейн проведёт 10 сентября прямую линию, совмещённую с пресс-конференцией | K56: Власть и кадровые решения | L56: Решение принято | M56: Ростислав Гольдштейн проведёт 10 сентября прямую линию, совмещённую с пресс-конференцией | U56: =IF(COUNTA(A56:T56)=0,"",IF(OR(A56="",B56="",C56="",E56="",G56="",H56="",J56="",K56="",L56="",M56=""),"Ошибка: заполните обязательные поля",IF(AND(LEFT(H56,7)<>"http://",LEFT(H56,8)<>"https://"),"Ошибка: некорректная ссылка",IF(COUNTIF($H$6:$H$1005,H56)>1,"Ошибка: дубликат URL",IF(E56>TODAY(),"Ошибка: дата публикации в будущем",IF(S56="Да","Ошибка: подтверждённый дубль",IF(S56="","Проверить: отметьте дубль",IF(S56="Нужно проверить","Проверить возможный дубль",IF(TODAY()-E56>30,"Проверить: старше 30 дней",IF(COUNTIFS(#REF!,G56,#REF!,"Готово")=0,"Проверить источник","Готово"))))))))))
A57: Python parser | B57: 2026-09-23 | C57: Республика Коми | E57: 2026-07-02 | G57: Министерство культуры и архивного дела Республики Коми | H57: https://mincult.rkomi.ru/documents/ | J57: Документы / Министерство культуры и архивного дела Республики Коми | K57: Культура | L57: Решение принято | M57: Приказ Министерства культуры и архивного дела РК от 30.12.2025 №701-од "Об утверждении Плана основных республиканских мероприятий Министерства культуры и архивного дела Республики Коми на 2026 год" Приложение. Приказ Министерства культуры и архивного дела РК от 05.11.2025 №602-од "О внесении изменений в приказ Министерства культуры и архивного дела Республики Коми от 14.10.2025 № 577-од «О некоторых вопросах реализации постановления Правительства Республики Коми от 09.11.2023 № 525 «О денежных поощрениях молодым творческим деятелям культуры и искусства»; Приказ Министерства культуры и архивного дела РК от 14.10.2025 №577-од "О некоторых вопросах реализации постановления Правительства Республики Коми от 09.11.2023 № 525 «О денежных поощрениях молодым творческим деятелям культуры и искусства» Приказ Министерства культуры и архивного дела РК от 01.10.2025 №556-од "О внесении изменений в приказ Министерства культуры и архивного дела Республики Коми от 13 декабря 2024 г. №642-од «Об утверждении Плана основных республиканских мероприятий Министерства культуры и архивного дела Республики Коми на 2025 год» | U57: =IF(COUNTA(A57:T57)=0,"",IF(OR(A57="",B57="",C57="",E57="",G57="",H57="",J57="",K57="",L57="",M57=""),"Ошибка: заполните обязательные поля",IF(AND(LEFT(H57,7)<>"http://",LEFT(H57,8)<>"https://"),"Ошибка: некорректная ссылка",IF(COUNTIF($H$6:$H$1005,H57)>1,"Ошибка: дубликат URL",IF(E57>TODAY(),"Ошибка: дата публикации в будущем",IF(S57="Да","Ошибка: подтверждённый дубль",IF(S57="","Проверить: отметьте дубль",IF(S57="Нужно проверить","Проверить возможный дубль",IF(TODAY()-E57>30,"Проверить: старше 30 дней",IF(COUNTIFS(#REF!,G57,#REF!,"Готово")=0,"Проверить источник","Готово"))))))))))
A58: Python parser | B58: 2026-09-23 | C58: Республика Коми | E58: 2026-07-02 | G58: Министерство культуры и архивного дела Республики Коми | H58: https://mincult.rkomi.ru/documents/all/ | J58: Документы / Министерство культуры и архивного дела Республики Коми | K58: Культура | L58: Решение принято | M58: Приказ Министерства культуры и архивного дела РК от 30.12.2025 №701-од "Об утверждении Плана основных республиканских мероприятий Министерства культуры и архивного дела Республики Коми на 2026 год" Приложение. Приказ Министерства культуры и архивного дела РК от 05.11.2025 №602-од "О внесении изменений в приказ Министерства культуры и архивного дела Республики Коми от 14.10.2025 № 577-од «О некоторых вопросах реализации постановления Правительства Республики Коми от 09.11.2023 № 525 «О денежных поощрениях молодым творческим деятелям культуры и искусства»; Приказ Министерства культуры и архивного дела РК от 14.10.2025 №577-од "О некоторых вопросах реализации постановления Правительства Республики Коми от 09.11.2023 № 525 «О денежных поощрениях молодым творческим деятелям культуры и искусства» Приказ Министерства культуры и архивного дела РК от 01.10.2025 №556-од "О внесении изменений в приказ Министерства культуры и архивного дела Республики Коми от 13 декабря 2024 г. №642-од «Об утверждении Плана основных республиканских мероприятий Министерства культуры и архивного дела Республики Коми на 2025 год» | U58: =IF(COUNTA(A58:T58)=0,"",IF(OR(A58="",B58="",C58="",E58="",G58="",H58="",J58="",K58="",L58="",M58=""),"Ошибка: заполните обязательные поля",IF(AND(LEFT(H58,7)<>"http://",LEFT(H58,8)<>"https://"),"Ошибка: некорректная ссылка",IF(COUNTIF($H$6:$H$1005,H58)>1,"Ошибка: дубликат URL",IF(E58>TODAY(),"Ошибка: дата публикации в будущем",IF(S58="Да","Ошибка: подтверждённый дубль",IF(S58="","Проверить: отметьте дубль",IF(S58="Нужно проверить","Проверить возможный дубль",IF(TODAY()-E58>30,"Проверить: старше 30 дней",IF(COUNTIFS(#REF!,G58,#REF!,"Готово")=0,"Проверить источник","Готово"))))))))))
A59: Python parser | B59: 2026-09-23 | C59: Республика Коми | E59: 2026-09-09 | G59: Министерство культуры и архивного дела Республики Коми | H59: https://mincult.rkomi.ru/presscenter/news/85576/ | J59: Команда Республики Коми: Марина Бурмистрова проинспектировала работу библиотек Прилузского района | K59: Культура | L59: Решение принято | M59: Руководитель ведомства Марина Бурмистрова посетила библиотеки Прилузского района, отметив профессионализм сотрудников и изменения в учреждениях культуры, связанные с национальным проектом «Культура» и «Семья». | N59: Библиотеки стали модельными благодаря национальным проектам; посещена Центральная детская библиотека и Центральная библиотека имени В.В. Юхнина; приобретены книги, интерактивное оборудование и современная мебель; созданы комфортные зоны для различных аудиторий. | O59: Марина Бурмистрова, Сергей Емельянов | P59: Министерство культуры Республики Коми, Прилузский район | R59: Прилузский район | U59: =IF(COUNTA(A59:T59)=0,"",IF(OR(A59="",B59="",C59="",E59="",G59="",H59="",J59="",K59="",L59="",M59=""),"Ошибка: заполните обязательные поля",IF(AND(LEFT(H59,7)<>"http://",LEFT(H59,8)<>"https://"),"Ошибка: некорректная ссылка",IF(COUNTIF($H$6:$H$1005,H59)>1,"Ошибка: дубликат URL",IF(E59>TODAY(),"Ошибка: дата публикации в будущем",IF(S59="Да","Ошибка: подтверждённый дубль",IF(S59="","Проверить: отметьте дубль",IF(S59="Нужно проверить","Проверить возможный дубль",IF(TODAY()-E59>30,"Проверить: старше 30 дней",IF(COUNTIFS(#REF!,G59,#REF!,"Готово")=0,"Проверить источник","Готово"))))))))))
A60: Python parser | B60: 2026-09-23 | C60: Республика Коми | E60: 2026-09-04 | G60: Министерство культуры и архивного дела Республики Коми | H60: https://mincult.rkomi.ru/presscenter/news/85427/ | J60: Республика Коми примет несколько Всероссийских фольклорно-этнографических экспедиций по выявлению объектов нематериального этнокультурного достояния | K60: Культура | M60: В Республике Коми пройдут две фольклорно-этнографические экспедиции под руководством известных ученых, направленные на выявление объектов нематериального этнокультурного достояния. | O60: Дмитрий Вайман, Галина Лобкова | P60: Институт гуманитарных исследований УрО РАН, Фольклорно-этнографический центр А.М. Мехнецова Санкт-Петербургской консерватории им. Н.А. Римского-Корсакова | R60: Прилузский район, Сыктывкар | U60: =IF(COUNTA(A60:T60)=0,"",IF(OR(A60="",B60="",C60="",E60="",G60="",H60="",J60="",K60="",L60="",M60=""),"Ошибка: заполните обязательные поля",IF(AND(LEFT(H60,7)<>"http://",LEFT(H60,8)<>"https://"),"Ошибка: некорректная ссылка",IF(COUNTIF($H$6:$H$1005,H60)>1,"Ошибка: дубликат URL",IF(E60>TODAY(),"Ошибка: дата публикации в будущем",IF(S60="Да","Ошибка: подтверждённый дубль",IF(S60="","Проверить: отметьте дубль",IF(S60="Нужно проверить","Проверить возможный дубль",IF(TODAY()-E60>30,"Проверить: старше 30 дней",IF(COUNTIFS(#REF!,G60,#REF!,"Готово")=0,"Проверить источник","Готово"))))))))))
A61: Python parser | B61: 2026-09-23 | C61: Республика Коми | E61: 2026-09-04 | G61: Министерство культуры и архивного дела Республики Коми | H61: https://mincult.rkomi.ru/presscenter/news/85608/ | J61: ЖКХ, дороги, здравоохранение: на Прямую линию с Главой Республики Коми Ростиславом Гольдштейном поступают вопросы жителей по самым актуальным темам | K61: Обращения и проблемы жителей | L61: Проблема / происшествие | M61: ЖКХ, дороги, здравоохранение: на Прямую линию с Главой Республики Коми Ростиславом Гольдштейном поступают вопросы жителей по самым актуальным темам | U61: =IF(COUNTA(A61:T61)=0,"",IF(OR(A61="",B61="",C61="",E61="",G61="",H61="",J61="",K61="",L61="",M61=""),"Ошибка: заполните обязательные поля",IF(AND(LEFT(H61,7)<>"http://",LEFT(H61,8)<>"https://"),"Ошибка: некорректная ссылка",IF(COUNTIF($H$6:$H$1005,H61)>1,"Ошибка: дубликат URL",IF(E61>TODAY(),"Ошибка: дата публикации в будущем",IF(S61="Да","Ошибка: подтверждённый дубль",IF(S61="","Проверить: отметьте дубль",IF(S61="Нужно проверить","Проверить возможный дубль",IF(TODAY()-E61>30,"Проверить: старше 30 дней",IF(COUNTIFS(#REF!,G61,#REF!,"Готово")=0,"Проверить источник","Готово"))))))))))
A62: Python parser | B62: 2026-09-23 | C62: Республика Коми | E62: 2026-09-03 | G62: Министерство культуры и архивного дела Республики Коми | H62: https://mincult.rkomi.ru/presscenter/news/85390/ | J62: Нацпроект «Семья»: в Объячево открылась новая модельная библиотека | K62: Культура | L62: Завершено / открыто | M62: В Прилузском районе открыта модельная библиотека нового поколения в рамках нацпроекта «Семья» | N62: Библиотека оснащена современным оборудованием и мебелью; мероприятие прошло при поддержке министра культуры Республики Коми | O62: Марина Бурмистрова - министр культуры и архивного дела Республики Коми | P62: Центральная межпоселенческая библиотека им. Василия Васильевича Юхнина, национальный проект «Семья» | R62: Прилузский район, село Объячево | U62: =IF(COUNTA(A62:T62)=0,"",IF(OR(A62="",B62="",C62="",E62="",G62="",H62="",J62="",K62="",L62="",M62=""),"Ошибка: заполните обязательные поля",IF(AND(LEFT(H62,7)<>"http://",LEFT(H62,8)<>"https://"),"Ошибка: некорректная ссылка",IF(COUNTIF($H$6:$H$1005,H62)>1,"Ошибка: дубликат URL",IF(E62>TODAY(),"Ошибка: дата публикации в будущем",IF(S62="Да","Ошибка: подтверждённый дубль",IF(S62="","Проверить: отметьте дубль",IF(S62="Нужно проверить","Проверить возможный дубль",IF(TODAY()-E62>30,"Проверить: старше 30 дней",IF(COUNTIFS(#REF!,G62,#REF!,"Готово")=0,"Проверить источник","Готово"))))))))))
A63: Python parser | B63: 2026-09-23 | C63: Республика Коми | E63: 2026-09-02 | G63: Министерство культуры и архивного дела Республики Коми | H63: https://mincult.rkomi.ru/presscenter/news/85368/ | J63: Коми впервые посетит Российский национальный молодёжный симфонический оркестр | K63: Культура | M63: Российский национальный молодёжный симфонический оркестр впервые проведёт гастрольный тур по Республике Коми, дав концерты в Сыктывкаре, Ухте и Воркуте. | O63: Марина Бурмистрова - министр культуры и архивного дела Республики Коми | P63: Российская национальная молодёжная симфоническая академия, Московская государственная академическая филармония | R63: Сыктывкар, Ухта, Воркута | U63: =IF(COUNTA(A63:T63)=0,"",IF(OR(A63="",B63="",C63="",E63="",G63="",H63="",J63="",K63="",L63="",M63=""),"Ошибка: заполните обязательные поля",IF(AND(LEFT(H63,7)<>"http://",LEFT(H63,8)<>"https://"),"Ошибка: некорректная ссылка",IF(COUNTIF($H$6:$H$1005,H63)>1,"Ошибка: дубликат URL",IF(E63>TODAY(),"Ошибка: дата публикации в будущем",IF(S63="Да","Ошибка: подтверждённый дубль",IF(S63="","Проверить: отметьте дубль",IF(S63="Нужно проверить","Проверить возможный дубль",IF(TODAY()-E63>30,"Проверить: старше 30 дней",IF(COUNTIFS(#REF!,G63,#REF!,"Готово")=0,"Проверить источник","Готово"))))))))))
A64: Python parser | B64: 2026-09-23 | C64: Республика Коми | E64: 2026-09-08 | G64: Министерство молодежной политики Республики Коми | H64: https://molodezh.rkomi.ru/presscenter/news/85549/ | J64: Восстанови имя: конкурс «Общая память» ищет исследователей геноцида советского народа | K64: Культура | M64: Проведение международного конкурса по поиску информации о жертвах геноцида советского народа во время Великой Отечественной войны. | P64: Национальный центр исторической памяти при Президенте РФ | U64: =IF(COUNTA(A64:T64)=0,"",IF(OR(A64="",B64="",C64="",E64="",G64="",H64="",J64="",K64="",L64="",M64=""),"Ошибка: заполните обязательные поля",IF(AND(LEFT(H64,7)<>"http://",LEFT(H64,8)<>"https://"),"Ошибка: некорректная ссылка",IF(COUNTIF($H$6:$H$1005,H64)>1,"Ошибка: дубликат URL",IF(E64>TODAY(),"Ошибка: дата публикации в будущем",IF(S64="Да","Ошибка: подтверждённый дубль",IF(S64="","Проверить: отметьте дубль",IF(S64="Нужно проверить","Проверить возможный дубль",IF(TODAY()-E64>30,"Проверить: старше 30 дней",IF(COUNTIFS(#REF!,G64,#REF!,"Готово")=0,"Проверить источник","Готово"))))))))))
A65: Python parser | B65: 2026-09-23 | C65: Республика Коми | E65: 2026-09-07 | G65: Министерство молодежной политики Республики Коми | H65: https://molodezh.rkomi.ru/presscenter/news/85548/ | J65: Станьте лучшим в трудоустройстве молодёжи: подайте заявку до 14 сентября | K65: Социальная сфера | L65: Анонс | M65: Минтруд России четвёртый год подряд проводит Всероссийский конкурс лучших практик трудоустройства молодёжи. Цель – найти и тиражировать успешные модели, которые помогают молодым людям находить работу, адаптироваться в профессии и строить карьеру. Участвовать могут коммерческие и некоммерческие организации, индивидуальные предприниматели, образовательные учреждения, государственные и муниципальные структуры, органы власти всех уровней. Один участник – одна номинация. Конкурс включает 12 номинаций – на любой профиль и масштаб: от трудоустройства подростков и стажировок до инклюзивных решений, работы с молодёжью в регионах, наставничества и корпоративных практик. Полный список – на сайте Минтруда. | U65: =IF(COUNTA(A65:T65)=0,"",IF(OR(A65="",B65="",C65="",E65="",G65="",H65="",J65="",K65="",L65="",M65=""),"Ошибка: заполните обязательные поля",IF(AND(LEFT(H65,7)<>"http://",LEFT(H65,8)<>"https://"),"Ошибка: некорректная ссылка",IF(COUNTIF($H$6:$H$1005,H65)>1,"Ошибка: дубликат URL",IF(E65>TODAY(),"Ошибка: дата публикации в будущем",IF(S65="Да","Ошибка: подтверждённый дубль",IF(S65="","Проверить: отметьте дубль",IF(S65="Нужно проверить","Проверить возможный дубль",IF(TODAY()-E65>30,"Проверить: старше 30 дней",IF(COUNTIFS(#REF!,G65,#REF!,"Готово")=0,"Проверить источник","Готово"))))))))))
A66: Python parser | B66: 2026-09-23 | C66: Республика Коми | E66: 2026-09-06 | G66: Министерство молодежной политики Республики Коми | H66: https://molodezh.rkomi.ru/presscenter/news/85545/ | J66: Измени свой город: конкурс «Юный Управдом» ждёт твои идеи | K66: Образование | L66: Анонс | M66: Хочешь, чтобы твой двор, улица или школа стали удобнее и безопаснее? У тебя есть шанс не просто предложить, а добиться реализации своей идеи. Стартовал приём заявок на IV Всероссийский конкурс «Юный Управдом – созидатель благоприятной среды проживания». К участию приглашают детей, подростков и молодых специалистов от 7 до 25 лет со всей страны. Загрузи свой проект на сайт konkurs-upravdom.ru до 9 ноября. Лучшие работы попадут в финал в Москве, где их оценят представители федеральных и региональных властей. А преокты победителей будут рекомендованы к реализации местным администрациям – твоя идея может изменить реальный двор или парк. Это не просто конкурс, а трамплин для твоей карьеры. Он входит в перечень Минпросвещения, и победа может принести дополнительные баллы к ЕГЭ при поступлении в вуз. За четыре года существования конкурса поступило около 2000 заявок, более 600 человек дошли до очного этапа. Присоединяйся к их числу. | U66: =IF(COUNTA(A66:T66)=0,"",IF(OR(A66="",B66="",C66="",E66="",G66="",H66="",J66="",K66="",L66="",M66=""),"Ошибка: заполните обязательные поля",IF(AND(LEFT(H66,7)<>"http://",LEFT(H66,8)<>"https://"),"Ошибка: некорректная ссылка",IF(COUNTIF($H$6:$H$1005,H66)>1,"Ошибка: дубликат URL",IF(E66>TODAY(),"Ошибка: дата публикации в будущем",IF(S66="Да","Ошибка: подтверждённый дубль",IF(S66="","Проверить: отметьте дубль",IF(S66="Нужно проверить","Проверить возможный дубль",IF(TODAY()-E66>30,"Проверить: старше 30 дней",IF(COUNTIFS(#REF!,G66,#REF!,"Готово")=0,"Проверить источник","Готово"))))))))))
A67: Python parser | B67: 2026-09-23 | C67: Республика Коми | E67: 2026-09-08 | G67: Министерство национальной политики Республики Коми | H67: https://minnats.rkomi.ru/presscenter/news/85568/ | J67: Единство народов России стало главной темой Православных Владимирских чтений в селе Усть-Кулом | K67: Культура | M67: В Усть-Куломском районе прошли XVII Православные Владимирские чтения, посвященные единству народов России и году села в Республике Коми. Мероприятия включали культурные объекты открытия, просветительские встречи, кинопоказы и дискуссии. | N67: Реализация культурного проекта при поддержке Президентского фонда культурных инициатив; показ фильма "Сила добра" по мотивам русской классики. | R67: село Усть-Кулом | U67: =IF(COUNTA(A67:T67)=0,"",IF(OR(A67="",B67="",C67="",E67="",G67="",H67="",J67="",K67="",L67="",M67=""),"Ошибка: заполните обязательные поля",IF(AND(LEFT(H67,7)<>"http://",LEFT(H67,8)<>"https://"),"Ошибка: некорректная ссылка",IF(COUNTIF($H$6:$H$1005,H67)>1,"Ошибка: дубликат URL",IF(E67>TODAY(),"Ошибка: дата публикации в будущем",IF(S67="Да","Ошибка: подтверждённый дубль",IF(S67="","Проверить: отметьте дубль",IF(S67="Нужно проверить","Проверить возможный дубль",IF(TODAY()-E67>30,"Проверить: старше 30 дней",IF(COUNTIFS(#REF!,G67,#REF!,"Готово")=0,"Проверить источник","Готово"))))))))))
A68: Python parser | B68: 2026-09-23 | C68: Республика Коми | E68: 2026-09-08 | G68: Министерство национальной политики Республики Коми | H68: https://minnats.rkomi.ru/presscenter/news/85493/ | J68: Фестиваль «Ми Танi Олам» и чествование нефтяников: министр национальной политики Коми Роман Носков посетил Усинск с рабочей поездкой | K68: Культура | L68: Проведение | M68: Министр национальной политики Республики Коми Роман Носков посетил Усинск, где принял участие в праздновании Дня работников нефтяной и газовой промышленности и II Муниципальном фестивале коми культуры «Ми Танi Олам» | N68: Фестиваль проходил на площади имени А. М. Босовой; участвовали населённые пункты округа Колва, Усть-Лыжа, Новикбож, Захарвань, Усть-Уса, Денисовка, Щельябож и Мутный Материк. | O68: Роман Носков (министр национальной политики Республики Коми); Ростислав Гольдштейн (Глава Республики Коми) | P68: Министерство национальной политики Республики Коми, компания «ЛУКОЙЛ» | R68: Усинск | U68: =IF(COUNTA(A68:T68)=0,"",IF(OR(A68="",B68="",C68="",E68="",G68="",H68="",J68="",K68="",L68="",M68=""),"Ошибка: заполните обязательные поля",IF(AND(LEFT(H68,7)<>"http://",LEFT(H68,8)<>"https://"),"Ошибка: некорректная ссылка",IF(COUNTIF($H$6:$H$1005,H68)>1,"Ошибка: дубликат URL",IF(E68>TODAY(),"Ошибка: дата публикации в будущем",IF(S68="Да","Ошибка: подтверждённый дубль",IF(S68="","Проверить: отметьте дубль",IF(S68="Нужно проверить","Проверить возможный дубль",IF(TODAY()-E68>30,"Проверить: старше 30 дней",IF(COUNTIFS(#REF!,G68,#REF!,"Готово")=0,"Проверить источник","Готово"))))))))))
A69: Python parser | B69: 2026-09-23 | C69: Республика Коми | E69: 2026-09-03 | G69: Министерство национальной политики Республики Коми | H69: https://minnats.rkomi.ru/presscenter/news/85404/ | J69: Диктант на языках народов России объединит жителей Коми | K69: Культура | M69: В Республике Коми проходит подготовка к всероссийскому диктанту «Россия – дом народов», приуроченному ко Дню языков народов Российской Федерации. | N69: На территории республики запланировано проведение диктанта на 96 муниципальных площадках; наибольшая активность ожидается в Сыктывкаре, Прилузском районе, Троицко-Печорском и Усть-Куломском районах; участие принимают школы, библиотеки, Дома культуры, университеты и учреждения среднего профессионального образования. | R69: Республика Коми | U69: =IF(COUNTA(A69:T69)=0,"",IF(OR(A69="",B69="",C69="",E69="",G69="",H69="",J69="",K69="",L69="",M69=""),"Ошибка: заполните обязательные поля",IF(AND(LEFT(H69,7)<>"http://",LEFT(H69,8)<>"https://"),"Ошибка: некорректная ссылка",IF(COUNTIF($H$6:$H$1005,H69)>1,"Ошибка: дубликат URL",IF(E69>TODAY(),"Ошибка: дата публикации в будущем",IF(S69="Да","Ошибка: подтверждённый дубль",IF(S69="","Проверить: отметьте дубль",IF(S69="Нужно проверить","Проверить возможный дубль",IF(TODAY()-E69>30,"Проверить: старше 30 дней",IF(COUNTIFS(#REF!,G69,#REF!,"Готово")=0,"Проверить источник","Готово"))))))))))
A70: Python parser | B70: 2026-09-23 | C70: Республика Коми | E70: 2026-09-03 | G70: Министерство национальной политики Республики Коми | H70: https://minnats.rkomi.ru/presscenter/news/85379/ | J70: Как задать вопрос Главе Коми? Ростислав Гольдштейн проведет прямую линию 10 сентября. | K70: Власть и кадровые решения | L70: Анонс | M70: Трансляцию покажут в социальной сети ВКонтакте, на телеканалах «Юрган» и «Коми гор». Задать вопрос можно: - по телефону: 8 800 200-96-14 (с 3 сентября) - через чат бот в МАХ: https://max.ru/hotlinekomi_bot - через систему ПОС на Госуслугах: https://pos.gosuslugi.ru/lkp/direct-line/13583/ - в аккаунте Ростислава Гольдштейна ВКонтакте под анонсом Прямые линии с гражданами проводятся во исполнение поручения Президента Российской Федерации Владимира Путина. Ростислав Гольдштейн подчеркнул, что такой формат является важнейшим инструментом прямой связи с жителями и оперативного реагирования на их запросы. Глава Республики Коми поручил Правительству Республики Коми закрепить в органах власти ответственных за отработку прямой линии, установить чёткие сроки подготовки ответов на обращения жителей и обеспечить регулярный контроль за исполнением. Пресс-служба Главы Республики Коми 167000, г.Сыктывкар, ул.Коммунистическая ,д.9 Телефон: (8212) 285-277, 285-401; Эл.почта: pressluzhba@adm.rkomi.ru | U70: =IF(COUNTA(A70:T70)=0,"",IF(OR(A70="",B70="",C70="",E70="",G70="",H70="",J70="",K70="",L70="",M70=""),"Ошибка: заполните обязательные поля",IF(AND(LEFT(H70,7)<>"http://",LEFT(H70,8)<>"https://"),"Ошибка: некорректная ссылка",IF(COUNTIF($H$6:$H$1005,H70)>1,"Ошибка: дубликат URL",IF(E70>TODAY(),"Ошибка: дата публикации в будущем",IF(S70="Да","Ошибка: подтверждённый дубль",IF(S70="","Проверить: отметьте дубль",IF(S70="Нужно проверить","Проверить возможный дубль",IF(TODAY()-E70>30,"Проверить: старше 30 дней",IF(COUNTIFS(#REF!,G70,#REF!,"Готово")=0,"Проверить источник","Готово"))))))))))
A71: Python parser | B71: 2026-09-23 | C71: Республика Коми | E71: 2026-09-09 | G71: Министерство образования и науки Республики Коми | H71: https://minobr.rkomi.ru/presscenter/news/85570/ | J71: От проводки до мурала: как преображается школа-интернат № 1 в Емве | K71: Образование | L71: Работы начаты | M71: В Специальной (коррекционной) школе-интернате № 1 города Емвы проводится капитальный ремонт с участием средств республиканского бюджета и национального проекта «Молодежь и дети», включающий реконструкцию инженерных систем, внутренних помещений и внешнего облика здания через мурал. | N71: Привлечены средства национального проекта; проведены демонтаж и стяжка пола, замена инженерных систем, внутренняя отделка, ремонт крыльца и площадки; ведутся отделочные работы, включая монтаж электропроводки, замену отопительной системы, установку подвесных потолков, окраску помещений, укладку линолеума и установку плинтусов. | P71: Специальная (коррекционная) школа-интернат № 1, Республика Коми, национальный проект «Молодежь и дети» | R71: Емва | U71: =IF(COUNTA(A71:T71)=0,"",IF(OR(A71="",B71="",C71="",E71="",G71="",H71="",J71="",K71="",L71="",M71=""),"Ошибка: заполните обязательные поля",IF(AND(LEFT(H71,7)<>"http://",LEFT(H71,8)<>"https://"),"Ошибка: некорректная ссылка",IF(COUNTIF($H$6:$H$1005,H71)>1,"Ошибка: дубликат URL",IF(E71>TODAY(),"Ошибка: дата публикации в будущем",IF(S71="Да","Ошибка: подтверждённый дубль",IF(S71="","Проверить: отметьте дубль",IF(S71="Нужно проверить","Проверить возможный дубль",IF(TODAY()-E71>30,"Проверить: старше 30 дней",IF(COUNTIFS(#REF!,G71,#REF!,"Готово")=0,"Проверить источник","Готово"))))))))))
A72: Python parser | B72: 2026-09-23 | C72: Республика Коми | E72: 2026-09-08 | G72: Министерство образования и науки Республики Коми | H72: https://minobr.rkomi.ru/presscenter/news/85571/ | J72: Готовность - 70 процентов: в воркутинской школе №35 капремонт идет активными темпами | K72: Строительство и инфраструктура | L72: Работы начаты | M72: В воркутинской школе №35 ведется капитальный ремонт, который уже достиг готовности 70%. Обновляются полы, устанавливаются окна, проводятся штукатурные работы и замена коммуникаций. | N72: Готовность ремонта - 70%, заменяются полы, окна, коммуникации; ведутся штукатурные работы; объект - школа №35 в Воркуте. | O72: Валентина Шукюрова - заместитель министра образования и науки Республики Коми | P72: Министерство образования и науки Республики Коми | R72: Воркута, Республика Коми | U72: =IF(COUNTA(A72:T72)=0,"",IF(OR(A72="",B72="",C72="",E72="",G72="",H72="",J72="",K72="",L72="",M72=""),"Ошибка: заполните обязательные поля",IF(AND(LEFT(H72,7)<>"http://",LEFT(H72,8)<>"https://"),"Ошибка: некорректная ссылка",IF(COUNTIF($H$6:$H$1005,H72)>1,"Ошибка: дубликат URL",IF(E72>TODAY(),"Ошибка: дата публикации в будущем",IF(S72="Да","Ошибка: подтверждённый дубль",IF(S72="","Проверить: отметьте дубль",IF(S72="Нужно проверить","Проверить возможный дубль",IF(TODAY()-E72>30,"Проверить: старше 30 дней",IF(COUNTIFS(#REF!,G72,#REF!,"Готово")=0,"Проверить источник","Готово"))))))))))
A73: Python parser | B73: 2026-09-23 | C73: Республика Коми | E73: 2026-09-08 | G73: Министерство образования и науки Республики Коми | H73: https://minobr.rkomi.ru/presscenter/news/85505/ | J73: В детских садах стартовали проекты «Орлята-дошколята» и «Добрые игры» | K73: Образование | M73: В детских садах Республики Коми стартовали проекты «Орлята-дошколята» и «Добрые игры», направленные на ознакомление детей с традиционными российскими духовно-нравственными ценностями. | O73: Сергей Кравцов - Министр просвещения РФ | R73: Республика Коми | U73: =IF(COUNTA(A73:T73)=0,"",IF(OR(A73="",B73="",C73="",E73="",G73="",H73="",J73="",K73="",L73="",M73=""),"Ошибка: заполните обязательные поля",IF(AND(LEFT(H73,7)<>"http://",LEFT(H73,8)<>"https://"),"Ошибка: некорректная ссылка",IF(COUNTIF($H$6:$H$1005,H73)>1,"Ошибка: дубликат URL",IF(E73>TODAY(),"Ошибка: дата публикации в будущем",IF(S73="Да","Ошибка: подтверждённый дубль",IF(S73="","Проверить: отметьте дубль",IF(S73="Нужно проверить","Проверить возможный дубль",IF(TODAY()-E73>30,"Проверить: старше 30 дней",IF(COUNTIFS(#REF!,G73,#REF!,"Готово")=0,"Проверить источник","Готово"))))))))))
A74: Python parser | B74: 2026-09-23 | C74: Республика Коми | E74: 2026-09-08 | G74: Министерство образования и науки Республики Коми | H74: https://minobr.rkomi.ru/presscenter/news/85495/ | J74: Педагогов приглашают принять участие во Всероссийском конкурсе «Атомный урок» | K74: Образование | L74: Анонс | M74: Всероссийский конкурс «Атомный урок» приглашает учителей и преподавателей принять участие, представив свои методические разработки и обменявшись опытом. | O74: Александр Бугаев - первый заместитель Министра просвещения РФ | P74: Министерство просвещения РФ, Госкорпорация «Росатом» | U74: =IF(COUNTA(A74:T74)=0,"",IF(OR(A74="",B74="",C74="",E74="",G74="",H74="",J74="",K74="",L74="",M74=""),"Ошибка: заполните обязательные поля",IF(AND(LEFT(H74,7)<>"http://",LEFT(H74,8)<>"https://"),"Ошибка: некорректная ссылка",IF(COUNTIF($H$6:$H$1005,H74)>1,"Ошибка: дубликат URL",IF(E74>TODAY(),"Ошибка: дата публикации в будущем",IF(S74="Да","Ошибка: подтверждённый дубль",IF(S74="","Проверить: отметьте дубль",IF(S74="Нужно проверить","Проверить возможный дубль",IF(TODAY()-E74>30,"Проверить: старше 30 дней",IF(COUNTIFS(#REF!,G74,#REF!,"Готово")=0,"Проверить источник","Готово"))))))))))
A75: Python parser | B75: 2026-09-23 | C75: Республика Коми | E75: 2026-09-07 | G75: Министерство образования и науки Республики Коми | H75: https://minobr.rkomi.ru/presscenter/news/85486/ | J75: Обновленная школа в деревне Денисовке встретила детей | K75: Образование | L75: Завершено / открыто | M75: В деревне Денисовка открылась обновленная сельская школа с новой мебелью, техникой и эстетически оформленными интерьерами. | N75: Школа расположена в Денисовке; капитальный ремонт проведен с учетом брендбука главы республики; использованы современные технологии и национальная символика; завершен ремонт трех сельских школ к Дню знаний. | O75: Ростислав Гольдштейн (Глава Республики Коми); Олег Холопов (Министр образования и науки Республики Коми) | P75: Министерство образования и науки Республики Коми | R75: Деревня Денисовка | U75: =IF(COUNTA(A75:T75)=0,"",IF(OR(A75="",B75="",C75="",E75="",G75="",H75="",J75="",K75="",L75="",M75=""),"Ошибка: заполните обязательные поля",IF(AND(LEFT(H75,7)<>"http://",LEFT(H75,8)<>"https://"),"Ошибка: некорректная ссылка",IF(COUNTIF($H$6:$H$1005,H75)>1,"Ошибка: дубликат URL",IF(E75>TODAY(),"Ошибка: дата публикации в будущем",IF(S75="Да","Ошибка: подтверждённый дубль",IF(S75="","Проверить: отметьте дубль",IF(S75="Нужно проверить","Проверить возможный дубль",IF(TODAY()-E75>30,"Проверить: старше 30 дней",IF(COUNTIFS(#REF!,G75,#REF!,"Готово")=0,"Проверить источник","Готово"))))))))))
A76: Python parser | B76: 2026-09-23 | C76: Республика Коми | E76: 2026-09-07 | G76: Министерство образования и науки Республики Коми | H76: https://minobr.rkomi.ru/presscenter/news/85480/ | J76: «Разговоры о важном» обрели новый формат | K76: Образование | M76: В школах и колледжах Республики Коми стартовал обновленный курс 'Разговоры о важном', который знакомит учеников и студентов с выдающимися деятелями России через биографические фильмы. | N76: Новый курс включает 28 уникальных тем; первый урок был посвящен Николаю Путилову; ученики 6-11 классов и студенты колледжей участвуют в курсе. | O76: Сергей Кравцов - Министр просвещения РФ | P76: Министерство просвещения РФ, школы, колледжи и техникумы Республики Коми | R76: Республика Коми | U76: =IF(COUNTA(A76:T76)=0,"",IF(OR(A76="",B76="",C76="",E76="",G76="",H76="",J76="",K76="",L76="",M76=""),"Ошибка: заполните обязательные поля",IF(AND(LEFT(H76,7)<>"http://",LEFT(H76,8)<>"https://"),"Ошибка: некорректная ссылка",IF(COUNTIF($H$6:$H$1005,H76)>1,"Ошибка: дубликат URL",IF(E76>TODAY(),"Ошибка: дата публикации в будущем",IF(S76="Да","Ошибка: подтверждённый дубль",IF(S76="","Проверить: отметьте дубль",IF(S76="Нужно проверить","Проверить возможный дубль",IF(TODAY()-E76>30,"Проверить: старше 30 дней",IF(COUNTIFS(#REF!,G76,#REF!,"Готово")=0,"Проверить источник","Готово"))))))))))
A77: Python parser | B77: 2026-09-23 | C77: Республика Коми | E77: 2026-09-07 | G77: Министерство образования и науки Республики Коми | H77: https://minobr.rkomi.ru/presscenter/news/85471/ | J77: Сергей Кравцов: «Работа по созданию единой системы профориентации в школе фактически завершена» | K77: Образование | L77: Решение принято | M77: Министр просвещения РФ Сергей Кравцов сообщил о завершении работы над созданием единой системы профориентации в школах, включающей специализированные уроки, посещения предприятий и онлайн-диагностику способностей школьников. | O77: Сергей Кравцов | R77: Республика Коми | U77: =IF(COUNTA(A77:T77)=0,"",IF(OR(A77="",B77="",C77="",E77="",G77="",H77="",J77="",K77="",L77="",M77=""),"Ошибка: заполните обязательные поля",IF(AND(LEFT(H77,7)<>"http://",LEFT(H77,8)<>"https://"),"Ошибка: некорректная ссылка",IF(COUNTIF($H$6:$H$1005,H77)>1,"Ошибка: дубликат URL",IF(E77>TODAY(),"Ошибка: дата публикации в будущем",IF(S77="Да","Ошибка: подтверждённый дубль",IF(S77="","Проверить: отметьте дубль",IF(S77="Нужно проверить","Проверить возможный дубль",IF(TODAY()-E77>30,"Проверить: старше 30 дней",IF(COUNTIFS(#REF!,G77,#REF!,"Готово")=0,"Проверить источник","Готово"))))))))))
A78: Python parser | B78: 2026-09-23 | C78: Республика Коми | E78: 2026-09-09 | G78: Министерство природных ресурсов и экологии Республики Коми | H78: https://mpr.rkomi.ru/ | J78: Министерство природных ресурсов и экологии Республики Коми | K78: Экология | M78: Проведение общественных обсуждений по проектам об обустройства месторождений и строительству трубопровода, включающих оценку воздействия на окружающую среду. | R78: Республика Коми | U78: =IF(COUNTA(A78:T78)=0,"",IF(OR(A78="",B78="",C78="",E78="",G78="",H78="",J78="",K78="",L78="",M78=""),"Ошибка: заполните обязательные поля",IF(AND(LEFT(H78,7)<>"http://",LEFT(H78,8)<>"https://"),"Ошибка: некорректная ссылка",IF(COUNTIF($H$6:$H$1005,H78)>1,"Ошибка: дубликат URL",IF(E78>TODAY(),"Ошибка: дата публикации в будущем",IF(S78="Да","Ошибка: подтверждённый дубль",IF(S78="","Проверить: отметьте дубль",IF(S78="Нужно проверить","Проверить возможный дубль",IF(TODAY()-E78>30,"Проверить: старше 30 дней",IF(COUNTIFS(#REF!,G78,#REF!,"Готово")=0,"Проверить источник","Готово"))))))))))
A79: Python parser | B79: 2026-09-23 | C79: Республика Коми | E79: 2026-09-09 | G79: Министерство природных ресурсов и экологии Республики Коми | H79: https://mpr.rkomi.ru/presscenter/news/85592/ | J79: Минприроды Республики Коми приглашает принять участие во всероссийской акции «Сохраним лес» | K79: Экология | L79: Анонс | M79: Минприроды Республики Коми проводит акцию 'Сохраним лес' по посадке деревьев, приуроченную к национальному проекту 'Экологическое благополучие'. Мероприятие пройдет 12 сентября 2026 года. | N79: За 7 сезонов акция позволила высадить более 430 млн деревьев; мероприятие состоится в квартале 14, выдел 8 Железнодорожного лесничества Кылтовского участкового лесничества; участники акции включают представителей правительства, сотрудников коммерческих организаций, волонтеров и специалистов лесного хозяйства. | P79: Минприроды Республики Коми, Правительство Республики Коми, ГАУ РК «Коми лесопожарный центр», КРОО «Общество лесоводов» | R79: Железнодорожное лесничество Кылтовского участкового лесничества, квартал 14, выдел 8 | U79: =IF(COUNTA(A79:T79)=0,"",IF(OR(A79="",B79="",C79="",E79="",G79="",H79="",J79="",K79="",L79="",M79=""),"Ошибка: заполните обязательные поля",IF(AND(LEFT(H79,7)<>"http://",LEFT(H79,8)<>"https://"),"Ошибка: некорректная ссылка",IF(COUNTIF($H$6:$H$1005,H79)>1,"Ошибка: дубликат URL",IF(E79>TODAY(),"Ошибка: дата публикации в будущем",IF(S79="Да","Ошибка: подтверждённый дубль",IF(S79="","Проверить: отметьте дубль",IF(S79="Нужно проверить","Проверить возможный дубль",IF(TODAY()-E79>30,"Проверить: старше 30 дней",IF(COUNTIFS(#REF!,G79,#REF!,"Готово")=0,"Проверить источник","Готово"))))))))))
A80: Python parser | B80: 2026-09-23 | C80: Республика Коми | E80: 2026-09-09 | G80: Министерство природных ресурсов и экологии Республики Коми | H80: https://mpr.rkomi.ru/presscenter/news/85591/ | J80: На страже нельмы: в Печорском районе обозначили границы заказника «Конецбор-Даниловский» | K80: Экология | L80: Завершено / открыто | M80: В заказнике «Конецбор-Даниловский» установлены информационные аншлаги с информацией о границах и правилах охраны для защиты редкой рыбы нельмы. | P80: АО «Транснефть-Север», государственный природный заказник «Конецбор-Даниловский» | R80: Печорский район | U80: =IF(COUNTA(A80:T80)=0,"",IF(OR(A80="",B80="",C80="",E80="",G80="",H80="",J80="",K80="",L80="",M80=""),"Ошибка: заполните обязательные поля",IF(AND(LEFT(H80,7)<>"http://",LEFT(H80,8)<>"https://"),"Ошибка: некорректная ссылка",IF(COUNTIF($H$6:$H$1005,H80)>1,"Ошибка: дубликат URL",IF(E80>TODAY(),"Ошибка: дата публикации в будущем",IF(S80="Да","Ошибка: подтверждённый дубль",IF(S80="","Проверить: отметьте дубль",IF(S80="Нужно проверить","Проверить возможный дубль",IF(TODAY()-E80>30,"Проверить: старше 30 дней",IF(COUNTIFS(#REF!,G80,#REF!,"Готово")=0,"Проверить источник","Готово"))))))))))
A81: Python parser | B81: 2026-09-23 | C81: Республика Коми | E81: 2026-09-09 | G81: Министерство природных ресурсов и экологии Республики Коми | H81: https://mpr.rkomi.ru/presscenter/news/85506/ | J81: На страже нельмы: в Печорском районе обозначили границы заказника «Конецбор-Даниловский» | K81: Экология | L81: Завершено / открыто | M81: В заказнике «Конецбор-Даниловский» установлены информационные аншлаги с информацией о границах и правилах охраны для защиты редких видов рыб, включая нельму. | N81: Заказник создан для охраны нельмы; установлены аншлаги с информацией о границах и охране; мероприятие проведено совместно с АО «Транснефть-Север». | P81: АО «Транснефть-Север», Государственный природный заказник «Конецбор-Даниловский» | R81: Печорский район | U81: =IF(COUNTA(A81:T81)=0,"",IF(OR(A81="",B81="",C81="",E81="",G81="",H81="",J81="",K81="",L81="",M81=""),"Ошибка: заполните обязательные поля",IF(AND(LEFT(H81,7)<>"http://",LEFT(H81,8)<>"https://"),"Ошибка: некорректная ссылка",IF(COUNTIF($H$6:$H$1005,H81)>1,"Ошибка: дубликат URL",IF(E81>TODAY(),"Ошибка: дата публикации в будущем",IF(S81="Да","Ошибка: подтверждённый дубль",IF(S81="","Проверить: отметьте дубль",IF(S81="Нужно проверить","Проверить возможный дубль",IF(TODAY()-E81>30,"Проверить: старше 30 дней",IF(COUNTIFS(#REF!,G81,#REF!,"Готово")=0,"Проверить источник","Готово"))))))))))
A82: Python parser | B82: 2026-09-23 | C82: Республика Коми | E82: 2026-09-08 | G82: Министерство природных ресурсов и экологии Республики Коми | H82: https://mpr.rkomi.ru/presscenter/news/85590/ | J82: За чистоту и порядок: уборка в заказнике «Белый» 11 сентября | K82: Экология | L82: Анонс | M82: Минприроды Республики Коми проводит республиканский этап Всероссийского субботника «Зелёная Россия» с целью уборки территории и воспитания экологической культуры. | O82: Минприроды Республики Коми | R82: заказник «Белый», Республика Коми | U82: =IF(COUNTA(A82:T82)=0,"",IF(OR(A82="",B82="",C82="",E82="",G82="",H82="",J82="",K82="",L82="",M82=""),"Ошибка: заполните обязательные поля",IF(AND(LEFT(H82,7)<>"http://",LEFT(H82,8)<>"https://"),"Ошибка: некорректная ссылка",IF(COUNTIF($H$6:$H$1005,H82)>1,"Ошибка: дубликат URL",IF(E82>TODAY(),"Ошибка: дата публикации в будущем",IF(S82="Да","Ошибка: подтверждённый дубль",IF(S82="","Проверить: отметьте дубль",IF(S82="Нужно проверить","Проверить возможный дубль",IF(TODAY()-E82>30,"Проверить: старше 30 дней",IF(COUNTIFS(#REF!,G82,#REF!,"Готово")=0,"Проверить источник","Готово"))))))))))
A83: Python parser | B83: 2026-09-23 | C83: Республика Коми | E83: 2026-09-08 | G83: Министерство природных ресурсов и экологии Республики Коми | H83: https://mpr.rkomi.ru/presscenter/news/85527/ | J83: «На связи с территорией: рабочая поездка министра в Усть-Куломский район» | K83: Власть и кадровые решения | L83: Решение принято | M83: Министр природных ресурсов и экологии Республики Коми посетил Усть-Куломский район для проверки исполнения поручений и оценки мер по улучшению качества жизни населения. | O83: Роман Полшведкин (министр природных ресурсов и экологии Республики Коми), Ростислав Гольдштейн (глава региона) | P83: Штаб общественной поддержки «Команда Республики Коми», администрация Усть-Куломского района | R83: Усть-Куломский район | U83: =IF(COUNTA(A83:T83)=0,"",IF(OR(A83="",B83="",C83="",E83="",G83="",H83="",J83="",K83="",L83="",M83=""),"Ошибка: заполните обязательные поля",IF(AND(LEFT(H83,7)<>"http://",LEFT(H83,8)<>"https://"),"Ошибка: некорректная ссылка",IF(COUNTIF($H$6:$H$1005,H83)>1,"Ошибка: дубликат URL",IF(E83>TODAY(),"Ошибка: дата публикации в будущем",IF(S83="Да","Ошибка: подтверждённый дубль",IF(S83="","Проверить: отметьте дубль",IF(S83="Нужно проверить","Проверить возможный дубль",IF(TODAY()-E83>30,"Проверить: старше 30 дней",IF(COUNTIFS(#REF!,G83,#REF!,"Готово")=0,"Проверить источник","Готово"))))))))))
A84: Python parser | B84: 2026-09-23 | C84: Республика Коми | E84: 2026-09-08 | G84: Министерство природных ресурсов и экологии Республики Коми | H84: https://mpr.rkomi.ru/presscenter/news/85503/ | J84: Четыре мешка мусора и одно нарушение: итоги уборки в заказнике «Белый» | K84: Экология | L84: Проблема / происшествие | M84: Сотрудники Минприроды и Центра по ООПТ провели уборку в заказнике «Белый» и собрали мусор, зафиксировав также нарушение режима особой охраны | N84: Собрано 4 мешка мусора, основная часть отходов — пластиковые бутылки и влажные салфетки; выявлено нарушение режима особой охраны — стоянка транспортного средства в неположенном месте | R84: заказник «Белый» | U84: =IF(COUNTA(A84:T84)=0,"",IF(OR(A84="",B84="",C84="",E84="",G84="",H84="",J84="",K84="",L84="",M84=""),"Ошибка: заполните обязательные поля",IF(AND(LEFT(H84,7)<>"http://",LEFT(H84,8)<>"https://"),"Ошибка: некорректная ссылка",IF(COUNTIF($H$6:$H$1005,H84)>1,"Ошибка: дубликат URL",IF(E84>TODAY(),"Ошибка: дата публикации в будущем",IF(S84="Да","Ошибка: подтверждённый дубль",IF(S84="","Проверить: отметьте дубль",IF(S84="Нужно проверить","Проверить возможный дубль",IF(TODAY()-E84>30,"Проверить: старше 30 дней",IF(COUNTIFS(#REF!,G84,#REF!,"Готово")=0,"Проверить источник","Готово"))))))))))
A85: Python parser | B85: 2026-09-23 | C85: Республика Коми | E85: 2026-09-08 | G85: Министерство природных ресурсов и экологии Республики Коми | H85: https://mpr.rkomi.ru/presscenter/news/85499/ | J85: ЖКХ, дороги, здравоохранение: на Прямую линию с Главой Республики Коми Ростиславом Гольдштейном поступают вопросы жителей по самым актуальным темам. | K85: Обращения и проблемы жителей | L85: Анонс | M85: На сегодняшний день поступило порядка 1000 обращений. Большинство из них касается качества предоставления жилищно-коммунальных услуг, состояния дорог и доступности медицинской помощи. Напомним, 10 сентября Глава Республики Коми Ростислав Гольдштейн проведёт Прямую линию, совмещённую с пресс-конференцией. Задать свой вопрос руководителю региона можно: | U85: =IF(COUNTA(A85:T85)=0,"",IF(OR(A85="",B85="",C85="",E85="",G85="",H85="",J85="",K85="",L85="",M85=""),"Ошибка: заполните обязательные поля",IF(AND(LEFT(H85,7)<>"http://",LEFT(H85,8)<>"https://"),"Ошибка: некорректная ссылка",IF(COUNTIF($H$6:$H$1005,H85)>1,"Ошибка: дубликат URL",IF(E85>TODAY(),"Ошибка: дата публикации в будущем",IF(S85="Да","Ошибка: подтверждённый дубль",IF(S85="","Проверить: отметьте дубль",IF(S85="Нужно проверить","Проверить возможный дубль",IF(TODAY()-E85>30,"Проверить: старше 30 дней",IF(COUNTIFS(#REF!,G85,#REF!,"Готово")=0,"Проверить источник","Готово"))))))))))
A86: Python parser | B86: 2026-09-23 | C86: Республика Коми | E86: 2026-09-07 | G86: Министерство природных ресурсов и экологии Республики Коми | H86: https://mpr.rkomi.ru/presscenter/news/85485/ | J86: Хрупкая красота под защитой: в заказнике «Скалы Каменки» появились аншлаги о редких растениях | K86: Экология | M86: В заказнике «Скалы Каменки» установлены аншлаги с информацией о редких растениях, включённых в Красную книгу Республики Коми. | N86: Виды растений: венерин башмачок настоящий, кизильник киноварно-красный, вероника колосистая; поддержка проекта: ООО «Инвест Трейд»; цель проекта: сохранение уникальных представителей флоры. | R86: заказник «Скалы Каменки», Печорский район | U86: =IF(COUNTA(A86:T86)=0,"",IF(OR(A86="",B86="",C86="",E86="",G86="",H86="",J86="",K86="",L86="",M86=""),"Ошибка: заполните обязательные поля",IF(AND(LEFT(H86,7)<>"http://",LEFT(H86,8)<>"https://"),"Ошибка: некорректная ссылка",IF(COUNTIF($H$6:$H$1005,H86)>1,"Ошибка: дубликат URL",IF(E86>TODAY(),"Ошибка: дата публикации в будущем",IF(S86="Да","Ошибка: подтверждённый дубль",IF(S86="","Проверить: отметьте дубль",IF(S86="Нужно проверить","Проверить возможный дубль",IF(TODAY()-E86>30,"Проверить: старше 30 дней",IF(COUNTIFS(#REF!,G86,#REF!,"Готово")=0,"Проверить источник","Готово"))))))))))
A87: Python parser | B87: 2026-09-23 | C87: Республика Коми | E87: 2026-09-10 | G87: Министерство сельского хозяйства и торговли Республики Коми | H87: https://mshp.rkomi.ru/ | J87: Министерство сельского хозяйства и торговли Республики Коми | K87: Экономика | M87: Министерство сельского хозяйства и торговли Республики Коми объявляет о продлении срока подачи заявок на конкурс по поддержке и финансированию проектов, направленных на защиту от атак беспилотников. | P87: Министерство сельского хозяйства и торговли Республики Коми, Попечительский совет Конкурса «Регионы – устойчивое развитие» | R87: Республика Коми | U87: =IF(COUNTA(A87:T87)=0,"",IF(OR(A87="",B87="",C87="",E87="",G87="",H87="",J87="",K87="",L87="",M87=""),"Ошибка: заполните обязательные поля",IF(AND(LEFT(H87,7)<>"http://",LEFT(H87,8)<>"https://"),"Ошибка: некорректная ссылка",IF(COUNTIF($H$6:$H$1005,H87)>1,"Ошибка: дубликат URL",IF(E87>TODAY(),"Ошибка: дата публикации в будущем",IF(S87="Да","Ошибка: подтверждённый дубль",IF(S87="","Проверить: отметьте дубль",IF(S87="Нужно проверить","Проверить возможный дубль",IF(TODAY()-E87>30,"Проверить: старше 30 дней",IF(COUNTIFS(#REF!,G87,#REF!,"Готово")=0,"Проверить источник","Готово"))))))))))
A88: Python parser | B88: 2026-09-23 | C88: Республика Коми | E88: 2026-09-10 | G88: Министерство сельского хозяйства и торговли Республики Коми | H88: https://mshp.rkomi.ru/presscenter/news/85619/ | J88: Воспитанники детского сада села Лэзым стали первопроходцами среди детсадов России | K88: Образование | M88: Воспитанники детского сада села Лэзым активно занимаются сельским хозяйством и принимают участие в всероссийских конкурсах и региональной выставке. | N88: На территории детского сада выращиваются различные сельскохозяйственные культуры; дети проводят эксперименты с овощами и собирают урожай; представлены экспериментальные сорта овощей и тыкв весом более 40 кг. | R88: Село Лэзым | U88: =IF(COUNTA(A88:T88)=0,"",IF(OR(A88="",B88="",C88="",E88="",G88="",H88="",J88="",K88="",L88="",M88=""),"Ошибка: заполните обязательные поля",IF(AND(LEFT(H88,7)<>"http://",LEFT(H88,8)<>"https://"),"Ошибка: некорректная ссылка",IF(COUNTIF($H$6:$H$1005,H88)>1,"Ошибка: дубликат URL",IF(E88>TODAY(),"Ошибка: дата публикации в будущем",IF(S88="Да","Ошибка: подтверждённый дубль",IF(S88="","Проверить: отметьте дубль",IF(S88="Нужно проверить","Проверить возможный дубль",IF(TODAY()-E88>30,"Проверить: старше 30 дней",IF(COUNTIFS(#REF!,G88,#REF!,"Готово")=0,"Проверить источник","Готово"))))))))))
A89: Python parser | B89: 2026-09-23 | C89: Республика Коми | E89: 2026-09-10 | G89: Министерство сельского хозяйства и торговли Республики Коми | H89: https://mshp.rkomi.ru/presscenter/news/85633/ | J89: Время объединяться: делегаты от Коми представят республику на финальном этапе Всероссийского марафона «Земля спорта – 2026» в Кисловодске | K89: Культура, спорт и туризм | L89: Решение принято | M89: Сборная команда Республики Коми сформирована и примет участие в финале Всероссийского марафона «Земля спорта – 2026» в Кисловодске. | O89: Роман Шуопис, Анастасия Шилова | R89: Усть-Вымский район, Сысольский район | U89: =IF(COUNTA(A89:T89)=0,"",IF(OR(A89="",B89="",C89="",E89="",G89="",H89="",J89="",K89="",L89="",M89=""),"Ошибка: заполните обязательные поля",IF(AND(LEFT(H89,7)<>"http://",LEFT(H89,8)<>"https://"),"Ошибка: некорректная ссылка",IF(COUNTIF($H$6:$H$1005,H89)>1,"Ошибка: дубликат URL",IF(E89>TODAY(),"Ошибка: дата публикации в будущем",IF(S89="Да","Ошибка: подтверждённый дубль",IF(S89="","Проверить: отметьте дубль",IF(S89="Нужно проверить","Проверить возможный дубль",IF(TODAY()-E89>30,"Проверить: старше 30 дней",IF(COUNTIFS(#REF!,G89,#REF!,"Готово")=0,"Проверить источник","Готово"))))))))))
A90: Python parser | B90: 2026-09-23 | C90: Республика Коми | E90: 2026-09-10 | G90: Министерство сельского хозяйства и торговли Республики Коми | H90: https://mshp.rkomi.ru/presscenter/news/85629/ | J90: Маркировка: изменения в законодательстве | K90: Экономика | L90: Решение принято | M90: С 1 августа 2026 года вводится обязательная маркировка готовых и консервированных мясных продуктов в Республике Коми, за исключением продукции крестьянских фермерских хозяйств и сельскохозяйственных производственных кооперативов. | N90: Дата начала обязательной маркировки - 1 августа 2026 года; Исключением являются продукты крестьянских фермерских хозяйств и сельскохозяйственных производственных кооперативов; Оператор ГИС мониторинга — ООО «ЦРПТ». | P90: Минсельхоз Коми, ООО «ЦРПТ» | U90: =IF(COUNTA(A90:T90)=0,"",IF(OR(A90="",B90="",C90="",E90="",G90="",H90="",J90="",K90="",L90="",M90=""),"Ошибка: заполните обязательные поля",IF(AND(LEFT(H90,7)<>"http://",LEFT(H90,8)<>"https://"),"Ошибка: некорректная ссылка",IF(COUNTIF($H$6:$H$1005,H90)>1,"Ошибка: дубликат URL",IF(E90>TODAY(),"Ошибка: дата публикации в будущем",IF(S90="Да","Ошибка: подтверждённый дубль",IF(S90="","Проверить: отметьте дубль",IF(S90="Нужно проверить","Проверить возможный дубль",IF(TODAY()-E90>30,"Проверить: старше 30 дней",IF(COUNTIFS(#REF!,G90,#REF!,"Готово")=0,"Проверить источник","Готово"))))))))))
A91: Python parser | B91: 2026-09-23 | C91: Республика Коми | E91: 2026-09-10 | G91: Министерство сельского хозяйства и торговли Республики Коми | H91: https://mshp.rkomi.ru/presscenter/news/85610/ | J91: За самую чистую разделку филе: мастер из Коми отмечен на главном состязании страны по обвалке оленины | K91: Экономика, бизнес и занятость | L91: Результат | M91: Мастер из Воркутинского производственного сельскохозяйственного кооператива «Оленевод» Александр Кубарев получил похвальную грамоту за успешное выступление на III Всероссийском конкурсе по обвалке оленины. | O91: Ростислав Гольдштейн, Александр Кубарев | P91: ПСК «Оленевод», Воркутинский производственный сельскохозяйственный кооператив «Оленевод» | U91: =IF(COUNTA(A91:T91)=0,"",IF(OR(A91="",B91="",C91="",E91="",G91="",H91="",J91="",K91="",L91="",M91=""),"Ошибка: заполните обязательные поля",IF(AND(LEFT(H91,7)<>"http://",LEFT(H91,8)<>"https://"),"Ошибка: некорректная ссылка",IF(COUNTIF($H$6:$H$1005,H91)>1,"Ошибка: дубликат URL",IF(E91>TODAY(),"Ошибка: дата публикации в будущем",IF(S91="Да","Ошибка: подтверждённый дубль",IF(S91="","Проверить: отметьте дубль",IF(S91="Нужно проверить","Проверить возможный дубль",IF(TODAY()-E91>30,"Проверить: старше 30 дней",IF(COUNTIFS(#REF!,G91,#REF!,"Готово")=0,"Проверить источник","Готово"))))))))))
A92: Python parser | B92: 2026-09-23 | C92: Республика Коми | E92: 2026-09-09 | G92: Министерство сельского хозяйства и торговли Республики Коми | H92: https://mshp.rkomi.ru/presscenter/news/85603/ | J92: «Одно окно» для фермеров: в Коми создадут единый цифровой сервис по учёту и маркировке животных в ЛПХ | K92: Экономика | L92: Решение принято | M92: В Республике Коми планируется создание единого цифрового сервиса 'одно окно' для учета и маркировки животных в личных подсобных хозяйствах. | O92: Ростислав Гольдштейн, Сергей Николаевич Елдин | P92: Министерство сельского хозяйства и торговли Республики Коми | R92: Республика Коми | U92: =IF(COUNTA(A92:T92)=0,"",IF(OR(A92="",B92="",C92="",E92="",G92="",H92="",J92="",K92="",L92="",M92=""),"Ошибка: заполните обязательные поля",IF(AND(LEFT(H92,7)<>"http://",LEFT(H92,8)<>"https://"),"Ошибка: некорректная ссылка",IF(COUNTIF($H$6:$H$1005,H92)>1,"Ошибка: дубликат URL",IF(E92>TODAY(),"Ошибка: дата публикации в будущем",IF(S92="Да","Ошибка: подтверждённый дубль",IF(S92="","Проверить: отметьте дубль",IF(S92="Нужно проверить","Проверить возможный дубль",IF(TODAY()-E92>30,"Проверить: старше 30 дней",IF(COUNTIFS(#REF!,G92,#REF!,"Готово")=0,"Проверить источник","Готово"))))))))))
A93: Python parser | B93: 2026-09-23 | C93: Республика Коми | E93: 2026-09-09 | G93: Министерство сельского хозяйства и торговли Республики Коми | H93: https://mshp.rkomi.ru/presscenter/news/85595/ | J93: Столица Коми вновь соберёт аграриев: на Стефановской площади будет представлен «Урожай-2026» | K93: Культура, спорт и туризм | L93: Анонс | M93: На Стефановской площади Сыктывкара пройдет конкурс-ярмарка "Урожай-2026", представляющая достижения агропромышленного комплекса Республики Коми. | O93: Ростислав Гольдштейн (Глава региона) | P93: Республика Коми, малые предприятия, крупные предприятия АПК | R93: Сыктывкар, Стефановская площадь | U93: =IF(COUNTA(A93:T93)=0,"",IF(OR(A93="",B93="",C93="",E93="",G93="",H93="",J93="",K93="",L93="",M93=""),"Ошибка: заполните обязательные поля",IF(AND(LEFT(H93,7)<>"http://",LEFT(H93,8)<>"https://"),"Ошибка: некорректная ссылка",IF(COUNTIF($H$6:$H$1005,H93)>1,"Ошибка: дубликат URL",IF(E93>TODAY(),"Ошибка: дата публикации в будущем",IF(S93="Да","Ошибка: подтверждённый дубль",IF(S93="","Проверить: отметьте дубль",IF(S93="Нужно проверить","Проверить возможный дубль",IF(TODAY()-E93>30,"Проверить: старше 30 дней",IF(COUNTIFS(#REF!,G93,#REF!,"Готово")=0,"Проверить источник","Готово"))))))))))
A94: Python parser | B94: 2026-09-23 | C94: Республика Коми | E94: 2026-09-09 | G94: Министерство сельского хозяйства и торговли Республики Коми | H94: https://mshp.rkomi.ru/presscenter/news/85586/ | J94: Гостеприимство по-коми: поддержка агротуризма – драйвера развития сельских территорий республики | K94: Культура, спорт и туризм | L94: Решение принято | M94: Глава Коми Ростислав Гольдштейн поддержал развитие агротуризма как инструмента комплексного развития сельских территорий и создания новых рабочих мест. Было поручено Минсельхозу оказать фермерам помощь в получении государственных грантов. | O94: Ростислав Гольдштейн, Сергей Елдин | P94: Минсельхоз Республики Коми | R94: Республика Коми | U94: =IF(COUNTA(A94:T94)=0,"",IF(OR(A94="",B94="",C94="",E94="",G94="",H94="",J94="",K94="",L94="",M94=""),"Ошибка: заполните обязательные поля",IF(AND(LEFT(H94,7)<>"http://",LEFT(H94,8)<>"https://"),"Ошибка: некорректная ссылка",IF(COUNTIF($H$6:$H$1005,H94)>1,"Ошибка: дубликат URL",IF(E94>TODAY(),"Ошибка: дата публикации в будущем",IF(S94="Да","Ошибка: подтверждённый дубль",IF(S94="","Проверить: отметьте дубль",IF(S94="Нужно проверить","Проверить возможный дубль",IF(TODAY()-E94>30,"Проверить: старше 30 дней",IF(COUNTIFS(#REF!,G94,#REF!,"Готово")=0,"Проверить источник","Готово"))))))))))
A95: Python parser | B95: 2026-09-23 | C95: Республика Коми | E95: 2026-09-09 | G95: Министерство сельского хозяйства и торговли Республики Коми | H95: https://mshp.rkomi.ru/presscenter/news/85579/ | J95: Сохраняя генофонд: в Коми соединяют традиции и современные технологии в племенном деле | K95: Сельское хозяйство | L95: Решение принято | M95: В Сыктывкаре прошло совещание по развитию племенного дела в Республике Коми, где обсуждались проблемы и перспективы отрасли. | N95: Совещание было посвящено развитию племенного дела; участники включали представителей власти, науки и агропромышленного комплекса; главной темой стало использование современных технологий в животноводстве. | O95: Сергей Елдин (Министр сельского хозяйства и торговли Коми); Ростислав Гольдштейн (Глава Республики Коми) | P95: РГУСП «Коми» по племенной работе | R95: Сыктывкар | U95: =IF(COUNTA(A95:T95)=0,"",IF(OR(A95="",B95="",C95="",E95="",G95="",H95="",J95="",K95="",L95="",M95=""),"Ошибка: заполните обязательные поля",IF(AND(LEFT(H95,7)<>"http://",LEFT(H95,8)<>"https://"),"Ошибка: некорректная ссылка",IF(COUNTIF($H$6:$H$1005,H95)>1,"Ошибка: дубликат URL",IF(E95>TODAY(),"Ошибка: дата публикации в будущем",IF(S95="Да","Ошибка: подтверждённый дубль",IF(S95="","Проверить: отметьте дубль",IF(S95="Нужно проверить","Проверить возможный дубль",IF(TODAY()-E95>30,"Проверить: старше 30 дней",IF(COUNTIFS(#REF!,G95,#REF!,"Готово")=0,"Проверить источник","Готово"))))))))))
A96: Python parser | B96: 2026-09-23 | C96: Республика Коми | E96: 2026-09-08 | G96: Министерство строительства и ЖКХ Республики Коми | H96: https://arch.rkomi.ru/presscenter/news/85556/ | J96: Минстрой начал обработку сообщений прямой линии Главы | K96: Обращения и проблемы жителей | L96: В процессе | M96: От жителей республики уже поступают вопросы в преддверии Прямой линии с Главой Республики Коми Ростиславом Гольдштейном, которая состоится 10 сентября 2026 года. Глава региона поручил реагировать на обращения максимально оперативно и качественно. В Минстрой Коми поступают обращения, связанные с улучшением жилищных условий граждан, в том числе переселение из ветхого аварийного жилья и реализация программы капитального ремонта многоквартирных домов. Также поступают вопросы по мерам государственной поддержки в виде предоставления гражданам социальных выплат на строительство или приобретение жилья. Все поступающие вопросы регистрируются в Министерстве. Некоторые ответы предоставляются в ходе индивидуальных телефонных консультаций. Ответы на обращения, требующие детальной проработки, будут даны в максимально сжатые сроки. | U96: =IF(COUNTA(A96:T96)=0,"",IF(OR(A96="",B96="",C96="",E96="",G96="",H96="",J96="",K96="",L96="",M96=""),"Ошибка: заполните обязательные поля",IF(AND(LEFT(H96,7)<>"http://",LEFT(H96,8)<>"https://"),"Ошибка: некорректная ссылка",IF(COUNTIF($H$6:$H$1005,H96)>1,"Ошибка: дубликат URL",IF(E96>TODAY(),"Ошибка: дата публикации в будущем",IF(S96="Да","Ошибка: подтверждённый дубль",IF(S96="","Проверить: отметьте дубль",IF(S96="Нужно проверить","Проверить возможный дубль",IF(TODAY()-E96>30,"Проверить: старше 30 дней",IF(COUNTIFS(#REF!,G96,#REF!,"Готово")=0,"Проверить источник","Готово"))))))))))
A97: Python parser | B97: 2026-09-23 | C97: Республика Коми | E97: 2026-09-04 | G97: Министерство строительства и ЖКХ Республики Коми | H97: https://arch.rkomi.ru/presscenter/news/85428/ | J97: Прямой диалог: Штаб общественной поддержки Команды Республики Коми организовал встречу жителей Сыктывдина с руководством Минстроя | K97: Власть и кадровые решения | L97: Проблема / происшествие | M97: Исполняющая обязанности министра Минстроя Республики Коми провела приём граждан в Сыктывдинском районе для обсуждения проблем переселения из аварийного жилья, капремонта МКД, благоустройства и газификации. | N97: Участие Штаба общественной поддержки Команды РК, личные приёмы граждан, контроль исполнения отдельных обращений. | O97: Анастасия Пихней (исполняющий обязанности министра строительства и ЖКХ РК) | P97: Штаб общественной поддержки Команды Республики Коми, Министерство строительства и ЖКХ Республики Коми | R97: Сыктывдинский район | U97: =IF(COUNTA(A97:T97)=0,"",IF(OR(A97="",B97="",C97="",E97="",G97="",H97="",J97="",K97="",L97="",M97=""),"Ошибка: заполните обязательные поля",IF(AND(LEFT(H97,7)<>"http://",LEFT(H97,8)<>"https://"),"Ошибка: некорректная ссылка",IF(COUNTIF($H$6:$H$1005,H97)>1,"Ошибка: дубликат URL",IF(E97>TODAY(),"Ошибка: дата публикации в будущем",IF(S97="Да","Ошибка: подтверждённый дубль",IF(S97="","Проверить: отметьте дубль",IF(S97="Нужно проверить","Проверить возможный дубль",IF(TODAY()-E97>30,"Проверить: старше 30 дней",IF(COUNTIFS(#REF!,G97,#REF!,"Готово")=0,"Проверить источник","Готово"))))))))))
A98: Python parser | B98: 2026-09-23 | C98: Республика Коми | E98: 2026-09-04 | G98: Министерство строительства и ЖКХ Республики Коми | H98: https://arch.rkomi.ru/presscenter/news/85424/ | J98: Финальный этап: строительство нового корпуса Республиканской инфекционной больницы готово на 95% | K98: Строительство и инфраструктура | L98: В процессе | M98: Строится новый корпус Республиканской инфекционной больницы, готовностью 95%, ведутся внутренние работы. | N98: Готовность объекта 95,25%; подрядчик ООО «ТетрастройКоми»; национальный проект «Продолжительная и активная жизнь»; личный контроль главы республики Ростислава Гольдштейна. | O98: Ростислав Гольдштейн (Глава Республики Коми); Владимир Путин (Президент России) | P98: ООО «ТетрастройКоми»; Республиканская инфекционная больница | R98: Республика Коми | U98: =IF(COUNTA(A98:T98)=0,"",IF(OR(A98="",B98="",C98="",E98="",G98="",H98="",J98="",K98="",L98="",M98=""),"Ошибка: заполните обязательные поля",IF(AND(LEFT(H98,7)<>"http://",LEFT(H98,8)<>"https://"),"Ошибка: некорректная ссылка",IF(COUNTIF($H$6:$H$1005,H98)>1,"Ошибка: дубликат URL",IF(E98>TODAY(),"Ошибка: дата публикации в будущем",IF(S98="Да","Ошибка: подтверждённый дубль",IF(S98="","Проверить: отметьте дубль",IF(S98="Нужно проверить","Проверить возможный дубль",IF(TODAY()-E98>30,"Проверить: старше 30 дней",IF(COUNTIFS(#REF!,G98,#REF!,"Готово")=0,"Проверить источник","Готово"))))))))))
A99: Python parser | B99: 2026-09-23 | C99: Республика Коми | E99: 2026-09-03 | G99: Министерство строительства и ЖКХ Республики Коми | H99: https://arch.rkomi.ru/presscenter/news/85405/ | J99: В Усть-Цильме благоустроили сельское кладбище | K99: Благоустройство | L99: Завершено / открыто | M99: В Усть-Цильме завершено благоустройство сельского кладбища «Нижнее» включая обновление ограждения, установку ворот и калитки, оканавливание территории и обустройство площадки. | N99: Выполнены работы по обновлению ограждения, установке ворот и калитки, оканниванию территории и обустройству площадок; проект реализован в рамках федерального проекта 'Формирование комфортной городской среды' нацпроекта 'Инфраструктура для жизни'. | O99: Ростислав Гольдштейн (Глава Коми) | P99: Администрация Усть-Цильмского сельского поселения, Администрация Республики Коми | R99: Усть-Цильма | U99: =IF(COUNTA(A99:T99)=0,"",IF(OR(A99="",B99="",C99="",E99="",G99="",H99="",J99="",K99="",L99="",M99=""),"Ошибка: заполните обязательные поля",IF(AND(LEFT(H99,7)<>"http://",LEFT(H99,8)<>"https://"),"Ошибка: некорректная ссылка",IF(COUNTIF($H$6:$H$1005,H99)>1,"Ошибка: дубликат URL",IF(E99>TODAY(),"Ошибка: дата публикации в будущем",IF(S99="Да","Ошибка: подтверждённый дубль",IF(S99="","Проверить: отметьте дубль",IF(S99="Нужно проверить","Проверить возможный дубль",IF(TODAY()-E99>30,"Проверить: старше 30 дней",IF(COUNTIFS(#REF!,G99,#REF!,"Готово")=0,"Проверить источник","Готово"))))))))))
A100: Python parser | B100: 2026-09-23 | C100: Республика Коми | E100: 2026-08-26 | G100: Министерство строительства и ЖКХ Республики Коми | H100: https://arch.rkomi.ru/presscenter/news/85089/ | J100: Прямая линия Главы Республики Коми | K100: Власть и кадровые решения | L100: Решение принято | M100: Ростислав Гольдштейн проведёт 10 сентября прямую линию, совмещённую с пресс-конференцией. Глава Республики Коми в прямом эфире ответит на вопросы жителей, а также представителей средств массовой информации и лидеров общественного мнения. Трансляцию покажут в социальной сети ВКонтакте, на телеканалах «Юрган» и «Коми гор». Прямые линии с гражданами проводятся во исполнение поручения Президента Российской Федерации Владимира Путина. Ростислав Гольдштейн подчеркнул, что такой формат является важнейшим инструментом прямой связи с жителями и оперативного реагирования на их запросы. | U100: =IF(COUNTA(A100:T100)=0,"",IF(OR(A100="",B100="",C100="",E100="",G100="",H100="",J100="",K100="",L100="",M100=""),"Ошибка: заполните обязательные поля",IF(AND(LEFT(H100,7)<>"http://",LEFT(H100,8)<>"https://"),"Ошибка: некорректная ссылка",IF(COUNTIF($H$6:$H$1005,H100)>1,"Ошибка: дубликат URL",IF(E100>TODAY(),"Ошибка: дата публикации в будущем",IF(S100="Да","Ошибка: подтверждённый дубль",IF(S100="","Проверить: отметьте дубль",IF(S100="Нужно проверить","Проверить возможный дубль",IF(TODAY()-E100>30,"Проверить: старше 30 дней",IF(COUNTIFS(#REF!,G100,#REF!,"Готово")=0,"Проверить источник","Готово"))))))))))
A101: Python parser | B101: 2026-09-23 | C101: Республика Коми | E101: 2026-09-03 | G101: Министерство тарифного регулирования Республики Коми | H101: https://komirec.rkomi.ru/presscenter/news/85384/ | J101: Как задать вопрос Главе Коми? Ростислав Гольдштейн проведет прямую линию 10 сентября. | K101: Другое | L101: Анонс | M101: Ростислав Гольдштейн проведет прямую линию 10 сентября, где жители смогут задать вопросы главе Коми. | O101: Ростислав Гольдштейн | U101: =IF(COUNTA(A101:T101)=0,"",IF(OR(A101="",B101="",C101="",E101="",G101="",H101="",J101="",K101="",L101="",M101=""),"Ошибка: заполните обязательные поля",IF(AND(LEFT(H101,7)<>"http://",LEFT(H101,8)<>"https://"),"Ошибка: некорректная ссылка",IF(COUNTIF($H$6:$H$1005,H101)>1,"Ошибка: дубликат URL",IF(E101>TODAY(),"Ошибка: дата публикации в будущем",IF(S101="Да","Ошибка: подтверждённый дубль",IF(S101="","Проверить: отметьте дубль",IF(S101="Нужно проверить","Проверить возможный дубль",IF(TODAY()-E101>30,"Проверить: старше 30 дней",IF(COUNTIFS(#REF!,G101,#REF!,"Готово")=0,"Проверить источник","Готово"))))))))))
A102: Python parser | B102: 2026-09-23 | C102: Республика Коми | E102: 2026-08-26 | G102: Министерство тарифного регулирования Республики Коми | H102: https://komirec.rkomi.ru/presscenter/news/85093/ | J102: Ростислав Гольдштейн проведёт прямую линию 10 сентября | K102: Власть и кадровые решения | L102: Анонс | M102: Глава Республики Коми Ростислав Гольдштейн проведёт прямую линию, совмещённую с пресс-конференцией. Мероприятие состоится 10 сентября. Глава в прямом эфире ответит на вопросы жителей, представителей СМИ и лидеров общественного мнения. Трансляция пройдёт в социальной сети ВКонтакте, а также на телеканалах «Юрган» и «Коми гор». — через чат-бот в национальном мессенджере МАХ: https://max.ru/hotlinekomi_bot — через платформу обратной связи: https://pos.gosuslugi.ru/lkp/direct-line/13583/ — в аккаунте Главы Республики Коми в ВКонтакте (в комментариях к анонсу). | U102: =IF(COUNTA(A102:T102)=0,"",IF(OR(A102="",B102="",C102="",E102="",G102="",H102="",J102="",K102="",L102="",M102=""),"Ошибка: заполните обязательные поля",IF(AND(LEFT(H102,7)<>"http://",LEFT(H102,8)<>"https://"),"Ошибка: некорректная ссылка",IF(COUNTIF($H$6:$H$1005,H102)>1,"Ошибка: дубликат URL",IF(E102>TODAY(),"Ошибка: дата публикации в будущем",IF(S102="Да","Ошибка: подтверждённый дубль",IF(S102="","Проверить: отметьте дубль",IF(S102="Нужно проверить","Проверить возможный дубль",IF(TODAY()-E102>30,"Проверить: старше 30 дней",IF(COUNTIFS(#REF!,G102,#REF!,"Готово")=0,"Проверить источник","Готово"))))))))))
A103: Python parser | B103: 2026-09-23 | C103: Республика Коми | E103: 2026-09-07 | G103: Министерство труда и социальной защиты Республики Коми | H103: https://mintrudsoc.rkomi.ru/documents/ | J103: Документы / Министерство труда и социальной защиты Республики Коми | K103: Социальная сфера | L103: Решение принято | M103: Размещены нормативные правовые акты, принятые Министерством труда и социальной защиты Республики Коми после 1 октября 2025 года | P103: Министерство труда и социальной защиты Республики Коми | R103: Республика Коми | U103: =IF(COUNTA(A103:T103)=0,"",IF(OR(A103="",B103="",C103="",E103="",G103="",H103="",J103="",K103="",L103="",M103=""),"Ошибка: заполните обязательные поля",IF(AND(LEFT(H103,7)<>"http://",LEFT(H103,8)<>"https://"),"Ошибка: некорректная ссылка",IF(COUNTIF($H$6:$H$1005,H103)>1,"Ошибка: дубликат URL",IF(E103>TODAY(),"Ошибка: дата публикации в будущем",IF(S103="Да","Ошибка: подтверждённый дубль",IF(S103="","Проверить: отметьте дубль",IF(S103="Нужно проверить","Проверить возможный дубль",IF(TODAY()-E103>30,"Проверить: старше 30 дней",IF(COUNTIFS(#REF!,G103,#REF!,"Готово")=0,"Проверить источник","Готово"))))))))))
A104: Python parser | B104: 2026-09-23 | C104: Республика Коми | E104: 2026-09-07 | G104: Министерство труда и социальной защиты Республики Коми | H104: https://mintrudsoc.rkomi.ru/documents/all/ | J104: Документы / Министерство труда и социальной защиты Республики Коми | K104: Социальная сфера | M104: Размещены нормативные правовые акты, принятые Министерством труда и социальной защиты Республики Коми после определенной даты | P104: Министерство труда и социальной защиты Республики Коми | R104: Республика Коми | U104: =IF(COUNTA(A104:T104)=0,"",IF(OR(A104="",B104="",C104="",E104="",G104="",H104="",J104="",K104="",L104="",M104=""),"Ошибка: заполните обязательные поля",IF(AND(LEFT(H104,7)<>"http://",LEFT(H104,8)<>"https://"),"Ошибка: некорректная ссылка",IF(COUNTIF($H$6:$H$1005,H104)>1,"Ошибка: дубликат URL",IF(E104>TODAY(),"Ошибка: дата публикации в будущем",IF(S104="Да","Ошибка: подтверждённый дубль",IF(S104="","Проверить: отметьте дубль",IF(S104="Нужно проверить","Проверить возможный дубль",IF(TODAY()-E104>30,"Проверить: старше 30 дней",IF(COUNTIFS(#REF!,G104,#REF!,"Готово")=0,"Проверить источник","Готово"))))))))))
A105: Python parser | B105: 2026-09-23 | C105: Республика Коми | E105: 2026-09-10 | G105: Министерство труда и социальной защиты Республики Коми | H105: https://mintrudsoc.rkomi.ru/presscenter/news/85627/ | J105: Федеральные эксперты научат специалистов Коми новым методам сбережения семьи | K105: Социальная сфера | L105: Анонс | M105: В Сыктывкаре пройдет обучающий интенсив для руководителей детских учреждений Республики Коми и Кировской области по теме «семьесбережение» с участием федеральных экспертов. | N105: Тема интенсива — помощь проблемным семьям; мероприятие состоится 14-15 сентября; участники — руководители детских учреждений Коми и Кировской области; цель — смена подхода к работе с семьями, предотвращение изъятия детей из семей. | O105: Мария Львова-Белова — Уполномоченный при Президенте РФ по правам ребенка | P105: Детские учреждения Республики Коми и Кировской области | R105: Сыктывкар | U105: =IF(COUNTA(A105:T105)=0,"",IF(OR(A105="",B105="",C105="",E105="",G105="",H105="",J105="",K105="",L105="",M105=""),"Ошибка: заполните обязательные поля",IF(AND(LEFT(H105,7)<>"http://",LEFT(H105,8)<>"https://"),"Ошибка: некорректная ссылка",IF(COUNTIF($H$6:$H$1005,H105)>1,"Ошибка: дубликат URL",IF(E105>TODAY(),"Ошибка: дата публикации в будущем",IF(S105="Да","Ошибка: подтверждённый дубль",IF(S105="","Проверить: отметьте дубль",IF(S105="Нужно проверить","Проверить возможный дубль",IF(TODAY()-E105>30,"Проверить: старше 30 дней",IF(COUNTIFS(#REF!,G105,#REF!,"Готово")=0,"Проверить источник","Готово"))))))))))
A106: Python parser | B106: 2026-09-23 | C106: Республика Коми | E106: 2026-09-10 | G106: Министерство труда и социальной защиты Республики Коми | H106: https://mintrudsoc.rkomi.ru/presscenter/news/85620/ | J106: В Коми подвели итоги республиканского смотра-конкурса на лучшее состояние условий и охраны труда в организациях за 2025 год | K106: Социальная сфера | L106: Результат | M106: В Коми завершили республиканский смотр-конкурс на лучшее состояние условий и охраны труда в организациях за 2025 год, победители определены среди производственных, непроизводственных и нефтегазовых компаний | N106: Участие 52 организаций; наибольшее количество заявок от Ухты и Сыктывкара | P106: организации-производственники, организации-непроизводственники, компании нефтегазовой отрасли | R106: Республика Коми | U106: =IF(COUNTA(A106:T106)=0,"",IF(OR(A106="",B106="",C106="",E106="",G106="",H106="",J106="",K106="",L106="",M106=""),"Ошибка: заполните обязательные поля",IF(AND(LEFT(H106,7)<>"http://",LEFT(H106,8)<>"https://"),"Ошибка: некорректная ссылка",IF(COUNTIF($H$6:$H$1005,H106)>1,"Ошибка: дубликат URL",IF(E106>TODAY(),"Ошибка: дата публикации в будущем",IF(S106="Да","Ошибка: подтверждённый дубль",IF(S106="","Проверить: отметьте дубль",IF(S106="Нужно проверить","Проверить возможный дубль",IF(TODAY()-E106>30,"Проверить: старше 30 дней",IF(COUNTIFS(#REF!,G106,#REF!,"Готово")=0,"Проверить источник","Готово"))))))))))
A107: Python parser | B107: 2026-09-23 | C107: Республика Коми | E107: 2026-09-08 | G107: Министерство труда и социальной защиты Республики Коми | H107: https://mintrudsoc.rkomi.ru/presscenter/news/85501/ | J107: В Коми меры поддержки на оплату ЖКУ получают 163,2 тысячи жителей республики | K107: Социальная сфера | M107: В Республике Коми 163,2 тысячи жителей получают меры поддержки на оплату жилищно-коммунальных услуг, включая региональные компенсации для многодетных семей и других льготных категорий граждан. | N107: Получатели: около 9 000 многодетных семей; 20 категорий граждан; размер компенсаций зависит от льготной категории и климатической зоны проживания. | O107: Ростислав Гольдштейн (руководитель региона); Татьяна Майкова (министр труда и социальной защиты Коми) | P107: Министерство труда и социальной защиты Коми | R107: Республика Коми | U107: =IF(COUNTA(A107:T107)=0,"",IF(OR(A107="",B107="",C107="",E107="",G107="",H107="",J107="",K107="",L107="",M107=""),"Ошибка: заполните обязательные поля",IF(AND(LEFT(H107,7)<>"http://",LEFT(H107,8)<>"https://"),"Ошибка: некорректная ссылка",IF(COUNTIF($H$6:$H$1005,H107)>1,"Ошибка: дубликат URL",IF(E107>TODAY(),"Ошибка: дата публикации в будущем",IF(S107="Да","Ошибка: подтверждённый дубль",IF(S107="","Проверить: отметьте дубль",IF(S107="Нужно проверить","Проверить возможный дубль",IF(TODAY()-E107>30,"Проверить: старше 30 дней",IF(COUNTIFS(#REF!,G107,#REF!,"Готово")=0,"Проверить источник","Готово"))))))))))
A108: Python parser | B108: 2026-09-23 | C108: Республика Коми | E108: 2026-09-03 | G108: Министерство труда и социальной защиты Республики Коми | H108: https://mintrudsoc.rkomi.ru/presscenter/news/85377/ | J108: В Коми семьи могут использовать региональный капитал для оплаты услуг, связанных с коррекцией развития ребенка | K108: Социальная сфера | L108: Решение принято | M108: В Республике Коми изменили законодательство, позволив семьям использовать региональный семейный капитал на оплату коррекционных услуг детям с особенностями развития. | N108: Региональный семейный капитал составляет до 50 тыс рублей, услуга предоставляется один раз в год. | O108: Ростислав Гольдштейн, Глава Республики Коми; Министерство труда и социальной защиты Республики Коми | R108: Республика Коми | U108: =IF(COUNTA(A108:T108)=0,"",IF(OR(A108="",B108="",C108="",E108="",G108="",H108="",J108="",K108="",L108="",M108=""),"Ошибка: заполните обязательные поля",IF(AND(LEFT(H108,7)<>"http://",LEFT(H108,8)<>"https://"),"Ошибка: некорректная ссылка",IF(COUNTIF($H$6:$H$1005,H108)>1,"Ошибка: дубликат URL",IF(E108>TODAY(),"Ошибка: дата публикации в будущем",IF(S108="Да","Ошибка: подтверждённый дубль",IF(S108="","Проверить: отметьте дубль",IF(S108="Нужно проверить","Проверить возможный дубль",IF(TODAY()-E108>30,"Проверить: старше 30 дней",IF(COUNTIFS(#REF!,G108,#REF!,"Готово")=0,"Проверить источник","Готово"))))))))))
A109: Python parser | B109: 2026-09-23 | C109: Республика Коми | E109: 2026-09-02 | G109: Министерство труда и социальной защиты Республики Коми | H109: https://mintrudsoc.rkomi.ru/presscenter/news/85300/ | J109: Как задать вопрос Главе Коми? Ростислав Гольдштейн проведет прямую линию 10 сентября | K109: Другое | L109: Анонс | M109: Ростислав Гольдштейн проведет прямую линию 10 сентября, где жители смогут задать вопросы главе Республики Коми. | O109: Ростислав Гольдштейн | R109: Республика Коми | U109: =IF(COUNTA(A109:T109)=0,"",IF(OR(A109="",B109="",C109="",E109="",G109="",H109="",J109="",K109="",L109="",M109=""),"Ошибка: заполните обязательные поля",IF(AND(LEFT(H109,7)<>"http://",LEFT(H109,8)<>"https://"),"Ошибка: некорректная ссылка",IF(COUNTIF($H$6:$H$1005,H109)>1,"Ошибка: дубликат URL",IF(E109>TODAY(),"Ошибка: дата публикации в будущем",IF(S109="Да","Ошибка: подтверждённый дубль",IF(S109="","Проверить: отметьте дубль",IF(S109="Нужно проверить","Проверить возможный дубль",IF(TODAY()-E109>30,"Проверить: старше 30 дней",IF(COUNTIFS(#REF!,G109,#REF!,"Готово")=0,"Проверить источник","Готово"))))))))))
A110: Python parser | B110: 2026-09-23 | C110: Республика Коми | E110: 2026-09-02 | G110: Министерство труда и социальной защиты Республики Коми | H110: https://mintrudsoc.rkomi.ru/presscenter/news/85268/ | J110: Многодетные семьи могут вернуть до 25 тысяч рублей за платное обучение детей в учреждениях СПО | K110: Социальная сфера | M110: Многодетные семьи в Республике Коми могут получить компенсацию до 25 000 рублей за платное обучение детей в учреждениях среднего профессионального образования. | N110: Компенсация составляет 50% от стоимости обучения; помощь предоставляется ежегодно; количество получивших компенсацию в прошлом учебном году – 243 семьи. | O110: Татьяна Майкова - министр труда и социальной защиты Республики Коми | P110: Минтрудсоц Республики Коми | R110: Республика Коми | U110: =IF(COUNTA(A110:T110)=0,"",IF(OR(A110="",B110="",C110="",E110="",G110="",H110="",J110="",K110="",L110="",M110=""),"Ошибка: заполните обязательные поля",IF(AND(LEFT(H110,7)<>"http://",LEFT(H110,8)<>"https://"),"Ошибка: некорректная ссылка",IF(COUNTIF($H$6:$H$1005,H110)>1,"Ошибка: дубликат URL",IF(E110>TODAY(),"Ошибка: дата публикации в будущем",IF(S110="Да","Ошибка: подтверждённый дубль",IF(S110="","Проверить: отметьте дубль",IF(S110="Нужно проверить","Проверить возможный дубль",IF(TODAY()-E110>30,"Проверить: старше 30 дней",IF(COUNTIFS(#REF!,G110,#REF!,"Готово")=0,"Проверить источник","Готово"))))))))))
...

Sheet Справочники
A1: Служебные справочники — не редактировать
A3: Муниципалитеты | B3: Категории | C3: Платформы | D3: Стадии | E3: Типы источников | F3: Официальность | G3: Активность | H3: Дубли
A4: Воркута | B4: Власть и кадровые решения | C4: Официальный сайт | D4: Анонс | E4: Администрация муниципалитета | F4: Подтверждено | G4: Активен | H4: Нет
A5: Вуктыл | B5: Бюджет и муниципальные финансы | C5: MAX | D5: Решение принято | E5: Глава муниципалитета | F5: Не подтверждено | G5: Неактивен | H5: Да
A6: Ижемский район | B6: Закупки и контракты | C6: ВКонтакте | D6: Финансирование выделено | E6: Совет / представительный орган | F6: Требует проверки | G6: Недоступен | H6: Нужно проверить
A7: Инта | B7: Строительство и инфраструктура | C7: Telegram | D7: Закупка объявлена | E7: Муниципальное учреждение | G7: Требует проверки
A8: Княжпогостский район | B8: ЖКХ и благоустройство | C8: Одноклассники | D8: Работы начаты | E8: Региональный орган власти
A9: Койгородский район | B9: Экономика, бизнес и занятость | C9: Rutube | D9: В процессе | E9: Официальная пресс-служба
A10: Корткеросский район | B10: Социальная сфера | C10: Другое | D10: Завершено / открыто | E10: Другое официальное
A11: Печора | B11: Образование | D11: Перенесено / приостановлено | E11: Неофициальный источник
A12: Прилузский район | B12: Здравоохранение | D12: Проблема / происшествие
A13: Сосногорск | B13: Происшествия и безопасность | D13: Результат
A14: Сыктывдинский район | B14: Экология
A15: Сыктывкар | B15: Обращения и проблемы жителей
A16: Сысольский район | B16: Культура, спорт и туризм
A17: Троицко-Печорский район | B17: Банки и финансовые сервисы
A18: Удорский район | B18: Другое
A19: Усинск
A20: Усть-Вымский район
A21: Усть-Куломский район
A22: Усть-Цилемский район
A23: Ухта
A24: Республика Коми

Sheet Контроль
A1: Контроль покрытия муниципалитетов — служебный лист
A2: Показатели рассчитываются автоматически по основному муниципалитету.
A3: Муниципалитет | B3: Всего источников | C3: Готовых источников | D3: Новостей за 30 дней | E3: Готовых новостей | F3: Нужно проверить | G3: Ошибки
A4: Воркута | B4: =COUNTIF(#REF!,A4) | C4: =COUNTIFS(#REF!,A4,#REF!,"Готово") | D4: =COUNTIFS(Новости!$C$6:$C$1005,A4,Новости!$E$6:$E$1005,">="&TODAY()-30) | E4: =COUNTIFS(Новости!$C$6:$C$1005,A4,Новости!$U$6:$U$1005,"Готово") | F4: =COUNTIFS(Новости!$C$6:$C$1005,A4,Новости!$U$6:$U$1005,"Проверить*") | G4: =COUNTIFS(Новости!$C$6:$C$1005,A4,Новости!$U$6:$U$1005,"Ошибка*")
A5: Вуктыл | B5: =COUNTIF(#REF!,A5) | C5: =COUNTIFS(#REF!,A5,#REF!,"Готово") | D5: =COUNTIFS(Новости!$C$6:$C$1005,A5,Новости!$E$6:$E$1005,">="&TODAY()-30) | E5: =COUNTIFS(Новости!$C$6:$C$1005,A5,Новости!$U$6:$U$1005,"Готово") | F5: =COUNTIFS(Новости!$C$6:$C$1005,A5,Новости!$U$6:$U$1005,"Проверить*") | G5: =COUNTIFS(Новости!$C$6:$C$1005,A5,Новости!$U$6:$U$1005,"Ошибка*")
A6: Ижемский район | B6: =COUNTIF(#REF!,A6) | C6: =COUNTIFS(#REF!,A6,#REF!,"Готово") | D6: =COUNTIFS(Новости!$C$6:$C$1005,A6,Новости!$E$6:$E$1005,">="&TODAY()-30) | E6: =COUNTIFS(Новости!$C$6:$C$1005,A6,Новости!$U$6:$U$1005,"Готово") | F6: =COUNTIFS(Новости!$C$6:$C$1005,A6,Новости!$U$6:$U$1005,"Проверить*") | G6: =COUNTIFS(Новости!$C$6:$C$1005,A6,Новости!$U$6:$U$1005,"Ошибка*")
A7: Инта | B7: =COUNTIF(#REF!,A7) | C7: =COUNTIFS(#REF!,A7,#REF!,"Готово") | D7: =COUNTIFS(Новости!$C$6:$C$1005,A7,Новости!$E$6:$E$1005,">="&TODAY()-30) | E7: =COUNTIFS(Новости!$C$6:$C$1005,A7,Новости!$U$6:$U$1005,"Готово") | F7: =COUNTIFS(Новости!$C$6:$C$1005,A7,Новости!$U$6:$U$1005,"Проверить*") | G7: =COUNTIFS(Новости!$C$6:$C$1005,A7,Новости!$U$6:$U$1005,"Ошибка*")
A8: Княжпогостский район | B8: =COUNTIF(#REF!,A8) | C8: =COUNTIFS(#REF!,A8,#REF!,"Готово") | D8: =COUNTIFS(Новости!$C$6:$C$1005,A8,Новости!$E$6:$E$1005,">="&TODAY()-30) | E8: =COUNTIFS(Новости!$C$6:$C$1005,A8,Новости!$U$6:$U$1005,"Готово") | F8: =COUNTIFS(Новости!$C$6:$C$1005,A8,Новости!$U$6:$U$1005,"Проверить*") | G8: =COUNTIFS(Новости!$C$6:$C$1005,A8,Новости!$U$6:$U$1005,"Ошибка*")
A9: Койгородский район | B9: =COUNTIF(#REF!,A9) | C9: =COUNTIFS(#REF!,A9,#REF!,"Готово") | D9: =COUNTIFS(Новости!$C$6:$C$1005,A9,Новости!$E$6:$E$1005,">="&TODAY()-30) | E9: =COUNTIFS(Новости!$C$6:$C$1005,A9,Новости!$U$6:$U$1005,"Готово") | F9: =COUNTIFS(Новости!$C$6:$C$1005,A9,Новости!$U$6:$U$1005,"Проверить*") | G9: =COUNTIFS(Новости!$C$6:$C$1005,A9,Новости!$U$6:$U$1005,"Ошибка*")
A10: Корткеросский район | B10: =COUNTIF(#REF!,A10) | C10: =COUNTIFS(#REF!,A10,#REF!,"Готово") | D10: =COUNTIFS(Новости!$C$6:$C$1005,A10,Новости!$E$6:$E$1005,">="&TODAY()-30) | E10: =COUNTIFS(Новости!$C$6:$C$1005,A10,Новости!$U$6:$U$1005,"Готово") | F10: =COUNTIFS(Новости!$C$6:$C$1005,A10,Новости!$U$6:$U$1005,"Проверить*") | G10: =COUNTIFS(Новости!$C$6:$C$1005,A10,Новости!$U$6:$U$1005,"Ошибка*")
A11: Печора | B11: =COUNTIF(#REF!,A11) | C11: =COUNTIFS(#REF!,A11,#REF!,"Готово") | D11: =COUNTIFS(Новости!$C$6:$C$1005,A11,Новости!$E$6:$E$1005,">="&TODAY()-30) | E11: =COUNTIFS(Новости!$C$6:$C$1005,A11,Новости!$U$6:$U$1005,"Готово") | F11: =COUNTIFS(Новости!$C$6:$C$1005,A11,Новости!$U$6:$U$1005,"Проверить*") | G11: =COUNTIFS(Новости!$C$6:$C$1005,A11,Новости!$U$6:$U$1005,"Ошибка*")
A12: Прилузский район | B12: =COUNTIF(#REF!,A12) | C12: =COUNTIFS(#REF!,A12,#REF!,"Готово") | D12: =COUNTIFS(Новости!$C$6:$C$1005,A12,Новости!$E$6:$E$1005,">="&TODAY()-30) | E12: =COUNTIFS(Новости!$C$6:$C$1005,A12,Новости!$U$6:$U$1005,"Готово") | F12: =COUNTIFS(Новости!$C$6:$C$1005,A12,Новости!$U$6:$U$1005,"Проверить*") | G12: =COUNTIFS(Новости!$C$6:$C$1005,A12,Новости!$U$6:$U$1005,"Ошибка*")
A13: Сосногорск | B13: =COUNTIF(#REF!,A13) | C13: =COUNTIFS(#REF!,A13,#REF!,"Готово") | D13: =COUNTIFS(Новости!$C$6:$C$1005,A13,Новости!$E$6:$E$1005,">="&TODAY()-30) | E13: =COUNTIFS(Новости!$C$6:$C$1005,A13,Новости!$U$6:$U$1005,"Готово") | F13: =COUNTIFS(Новости!$C$6:$C$1005,A13,Новости!$U$6:$U$1005,"Проверить*") | G13: =COUNTIFS(Новости!$C$6:$C$1005,A13,Новости!$U$6:$U$1005,"Ошибка*")
A14: Сыктывдинский район | B14: =COUNTIF(#REF!,A14) | C14: =COUNTIFS(#REF!,A14,#REF!,"Готово") | D14: =COUNTIFS(Новости!$C$6:$C$1005,A14,Новости!$E$6:$E$1005,">="&TODAY()-30) | E14: =COUNTIFS(Новости!$C$6:$C$1005,A14,Новости!$U$6:$U$1005,"Готово") | F14: =COUNTIFS(Новости!$C$6:$C$1005,A14,Новости!$U$6:$U$1005,"Проверить*") | G14: =COUNTIFS(Новости!$C$6:$C$1005,A14,Новости!$U$6:$U$1005,"Ошибка*")
A15: Сыктывкар | B15: =COUNTIF(#REF!,A15) | C15: =COUNTIFS(#REF!,A15,#REF!,"Готово") | D15: =COUNTIFS(Новости!$C$6:$C$1005,A15,Новости!$E$6:$E$1005,">="&TODAY()-30) | E15: =COUNTIFS(Новости!$C$6:$C$1005,A15,Новости!$U$6:$U$1005,"Готово") | F15: =COUNTIFS(Новости!$C$6:$C$1005,A15,Новости!$U$6:$U$1005,"Проверить*") | G15: =COUNTIFS(Новости!$C$6:$C$1005,A15,Новости!$U$6:$U$1005,"Ошибка*")
... A23: Ухта | B23: =COUNTIF(#REF!,A23) | C23: =COUNTIFS(#REF!,A23,#REF!,"Готово") | D23: =COUNTIFS(Новости!$C$6:$C$1005,A23,Новости!$E$6:$E$1005,">="&TODAY()-30) | E23: =COUNTIFS(Новости!$C$6:$C$1005,A23,Новости!$U$6:$U$1005,"Готово") | F23: =COUNTIFS(Новости!$C$6:$C$1005,A23,Новости!$U$6:$U$1005,"Проверить*") | G23: =COUNTIFS(Новости!$C$6:$C$1005,A23,Новости!$U$6:$U$1005,"Ошибка*")
A25: Итого | B25: =SUM(B4:B23) | C25: =SUM(C4:C23) | D25: =SUM(D4:D23) | E25: =SUM(E4:E23) | F25: =SUM(F4:F23) | G25: =SUM(G4:G23)
